[
  {
    "pos": {
      "x": -0.02435625,
      "y": 0.757232,
      "z": 3.708488
    },
    "rot": {
      "w": -4.371139e-8,
      "x": 0,
      "y": 1,
      "z": 0
    },
    "color": -8299003,
    "materialId": 0,
    "type": "1x4",
    "usingNewColor": true,
    "user": "a56d3b43eae48f9b33be2485279ee312"
  },
  {
    "pos": {
      "x": 0.115831,
      "y": 1.070676,
      "z": 3.175781
    },
    "rot": {
      "w": 0.7071069,
      "x": 0,
      "y": -0.7071067,
      "z": 0
    },
    "color": -8299003,
    "materialId": 0,
    "type": "1x10Plate",
    "usingNewColor": true,
    "user": "a56d3b43eae48f9b33be2485279ee312"
  },
  {
    "pos": {
      "x": -0.2486575,
      "y": 0.734996,
      "z": 3.400075
    },
    "rot": {
      "w": -1,
      "x": 0,
      "y": -8.742278e-8,
      "z": 0
    },
    "color": -11439553,
    "materialId": 0,
    "type": "2x4Plate",
    "usingNewColor": true,
    "user": "e745848173210df6969de43cb63418a5"
  },
  {
    "pos": {
      "x": -0.2486572,
      "y": 0.757232,
      "z": 3.708488
    },
    "rot": {
      "w": -4.371139e-8,
      "x": 0,
      "y": 1,
      "z": 0
    },
    "color": -8299003,
    "materialId": 0,
    "type": "1x4",
    "usingNewColor": true,
    "user": "a56d3b43eae48f9b33be2485279ee312"
  },
  {
    "pos": {
      "x": -0.7813714,
      "y": 0.757496,
      "z": -1.250184
    },
    "rot": {
      "w": 0.7071067,
      "x": 0,
      "y": 0.7071069,
      "z": 0
    },
    "color": -3815995,
    "materialId": 0,
    "type": "1x8Plate",
    "usingNewColor": true,
    "user": "e745848173210df6969de43cb63418a5"
  },
  {
    "pos": {
      "x": -0.1365066,
      "y": 0.9586399,
      "z": 3.708488
    },
    "rot": {
      "w": 1.311342e-7,
      "x": 0,
      "y": -1,
      "z": 0
    },
    "color": -7703232,
    "materialId": 0,
    "type": "1x2",
    "usingNewColor": true,
    "user": "a56d3b43eae48f9b33be2485279ee312"
  },
  {
    "pos": {
      "x": 0.115831,
      "y": 1.025776,
      "z": 3.512227
    },
    "rot": {
      "w": 0.7071069,
      "x": 0,
      "y": -0.7071067,
      "z": 0
    },
    "color": -8299003,
    "materialId": 0,
    "type": "1x4",
    "usingNewColor": true,
    "user": "a56d3b43eae48f9b33be2485279ee312"
  },
  {
    "pos": {
      "x": -0.08043177,
      "y": 0.734996,
      "z": 3.091662
    },
    "rot": {
      "w": -4.371139e-8,
      "x": 0,
      "y": 1,
      "z": 0
    },
    "color": -11439553,
    "materialId": 0,
    "type": "1x2Plate",
    "usingNewColor": true,
    "user": "e745848173210df6969de43cb63418a5"
  },
  {
    "pos": {
      "x": 0.03191976,
      "y": 0.8582399,
      "z": 2.755337
    },
    "rot": {
      "w": 5.205485e-7,
      "x": 0,
      "y": -1,
      "z": 0
    },
    "color": -8299003,
    "materialId": 0,
    "type": "1x2Window",
    "usingNewColor": true,
    "user": "a56d3b43eae48f9b33be2485279ee312"
  },
  {
    "pos": {
      "x": 0.4522819,
      "y": 0.757232,
      "z": -2.680104
    },
    "rot": {
      "w": -4.371139e-8,
      "x": 0,
      "y": 1,
      "z": 0
    },
    "color": -11439553,
    "materialId": 0,
    "type": "1x1",
    "usingNewColor": true,
    "user": "e745848173210df6969de43cb63418a5"
  },
  {
    "pos": {
      "x": -0.1365062,
      "y": 1.025776,
      "z": 3.708488
    },
    "rot": {
      "w": 1.311342e-7,
      "x": 0,
      "y": -1,
      "z": 0
    },
    "color": -7703232,
    "materialId": 0,
    "type": "1x2",
    "usingNewColor": true,
    "user": "a56d3b43eae48f9b33be2485279ee312"
  },
  {
    "pos": {
      "x": -0.3326697,
      "y": 0.802132,
      "z": 2.811286
    },
    "rot": {
      "w": -0.7071069,
      "x": 0,
      "y": 0.7071067,
      "z": 0
    },
    "color": -2619344,
    "materialId": 0,
    "type": "FlatPlant",
    "usingNewColor": true,
    "user": "e745848173210df6969de43cb63418a5"
  },
  {
    "pos": {
      "x": 0.1438061,
      "y": 0.8243679,
      "z": 3.175676
    },
    "rot": {
      "w": -0.7071068,
      "x": 0,
      "y": -0.7071069,
      "z": 0
    },
    "color": -8299003,
    "materialId": 0,
    "type": "2x8",
    "usingNewColor": true,
    "user": "a56d3b43eae48f9b33be2485279ee312"
  },
  {
    "pos": {
      "x": 0.115831,
      "y": 0.8243679,
      "z": 3.512226
    },
    "rot": {
      "w": 0.7071069,
      "x": 0,
      "y": -0.7071067,
      "z": 0
    },
    "color": -8299003,
    "materialId": 0,
    "type": "1x4",
    "usingNewColor": true,
    "user": "a56d3b43eae48f9b33be2485279ee312"
  },
  {
    "pos": {
      "x": -0.1364321,
      "y": 0.9586039,
      "z": 2.727362
    },
    "rot": {
      "w": -1,
      "x": 0,
      "y": -7.828169e-7,
      "z": 0
    },
    "color": -8299003,
    "materialId": 0,
    "type": "2x2",
    "usingNewColor": true,
    "user": "a56d3b43eae48f9b33be2485279ee312"
  },
  {
    "pos": {
      "x": 0.7326575,
      "y": 0.734996,
      "z": 2.53091
    },
    "rot": {
      "w": -0.7071068,
      "x": 0,
      "y": -0.7071069,
      "z": 0
    },
    "color": -2619344,
    "materialId": 0,
    "type": "FlatPlant",
    "usingNewColor": true,
    "user": "e745848173210df6969de43cb63418a5"
  },
  {
    "pos": {
      "x": 0.3401316,
      "y": 0.757232,
      "z": -2.73618
    },
    "rot": {
      "w": -4.371139e-8,
      "x": 0,
      "y": 1,
      "z": 0
    },
    "color": -11439553,
    "materialId": 0,
    "type": "1x1",
    "usingNewColor": true,
    "user": "e745848173210df6969de43cb63418a5"
  },
  {
    "pos": {
      "x": 0.1717809,
      "y": 0.913968,
      "z": 3.287626
    },
    "rot": {
      "w": -0.7071068,
      "x": 0,
      "y": -0.7071069,
      "z": 0
    },
    "color": -12991188,
    "materialId": 0,
    "type": "1x2_1FaceSideStud",
    "usingNewColor": true,
    "user": "a56d3b43eae48f9b33be2485279ee312"
  },
  {
    "pos": {
      "x": -0.2206196,
      "y": 0.8243679,
      "z": 3.708488
    },
    "rot": {
      "w": 1.311342e-7,
      "x": 0,
      "y": -1,
      "z": 0
    },
    "color": -8299003,
    "materialId": 0,
    "type": "1x1",
    "usingNewColor": true,
    "user": "a56d3b43eae48f9b33be2485279ee312"
  },
  {
    "pos": {
      "x": -0.4168821,
      "y": 0.734996,
      "z": -1.474488
    },
    "rot": {
      "w": -0.7071069,
      "x": 0,
      "y": 0.7071068,
      "z": 0
    },
    "color": -14252289,
    "materialId": 0,
    "type": "2x8Plate",
    "usingNewColor": true,
    "user": "e745848173210df6969de43cb63418a5"
  },
  {
    "pos": {
      "x": 0.1717808,
      "y": 0.8692679,
      "z": 3.035689
    },
    "rot": {
      "w": -0.7071069,
      "x": 0,
      "y": 0.7071066,
      "z": 0
    },
    "color": -12991188,
    "materialId": 0,
    "type": "FlatPlant",
    "usingNewColor": true,
    "user": "a56d3b43eae48f9b33be2485279ee312"
  },
  {
    "pos": {
      "x": 0.115831,
      "y": 0.8243679,
      "z": 2.783374
    },
    "rot": {
      "w": -0.7071067,
      "x": 0,
      "y": -0.7071069,
      "z": 0
    },
    "color": -8299003,
    "materialId": 0,
    "type": "1x2",
    "usingNewColor": true,
    "user": "a56d3b43eae48f9b33be2485279ee312"
  },
  {
    "pos": {
      "x": -0.8933211,
      "y": 0.802232,
      "z": -1.194114
    },
    "rot": {
      "w": -0.7071068,
      "x": 0,
      "y": -0.7071069,
      "z": 0
    },
    "color": -3815995,
    "materialId": 0,
    "type": "1x6",
    "usingNewColor": true,
    "user": "e745848173210df6969de43cb63418a5"
  },
  {
    "pos": {
      "x": -0.3327699,
      "y": 0.802132,
      "z": 3.708488
    },
    "rot": {
      "w": -0.7071067,
      "x": 0,
      "y": -0.7071069,
      "z": 0
    },
    "color": -2619344,
    "materialId": 0,
    "type": "FlatPlant",
    "usingNewColor": true,
    "user": "e745848173210df6969de43cb63418a5"
  },
  {
    "pos": {
      "x": -0.1925826,
      "y": 0.734996,
      "z": 3.568301
    },
    "rot": {
      "w": -0.7071068,
      "x": 0,
      "y": -0.7071069,
      "z": 0
    },
    "color": -11439553,
    "materialId": 0,
    "type": "2x4Plate",
    "usingNewColor": true,
    "user": "e745848173210df6969de43cb63418a5"
  },
  {
    "pos": {
      "x": -0.05219375,
      "y": 0.8243679,
      "z": 2.783248
    },
    "rot": {
      "w": -0.7071069,
      "x": 0,
      "y": 0.7071067,
      "z": 0
    },
    "color": -8299003,
    "materialId": 0,
    "type": "1x2",
    "usingNewColor": true,
    "user": "a56d3b43eae48f9b33be2485279ee312"
  },
  {
    "pos": {
      "x": 0.115831,
      "y": 0.757232,
      "z": 3.568301
    },
    "rot": {
      "w": -0.7071069,
      "x": 0,
      "y": 0.7071068,
      "z": 0
    },
    "color": -8299003,
    "materialId": 0,
    "type": "1x6",
    "usingNewColor": true,
    "user": "a56d3b43eae48f9b33be2485279ee312"
  },
  {
    "pos": {
      "x": -0.08043226,
      "y": 0.734996,
      "z": 2.951474
    },
    "rot": {
      "w": -0.7071068,
      "x": 0,
      "y": -0.7071069,
      "z": 0
    },
    "color": -11439553,
    "materialId": 0,
    "type": "2x4Plate",
    "usingNewColor": true,
    "user": "e745848173210df6969de43cb63418a5"
  },
  {
    "pos": {
      "x": 0.7887326,
      "y": 0.734996,
      "z": 2.474835
    },
    "rot": {
      "w": -1,
      "x": 0,
      "y": -8.742278e-8,
      "z": 0
    },
    "color": -2619344,
    "materialId": 0,
    "type": "FlatPlant",
    "usingNewColor": true,
    "user": "e745848173210df6969de43cb63418a5"
  },
  {
    "pos": {
      "x": -0.3327702,
      "y": 0.734996,
      "z": 2.867361
    },
    "rot": {
      "w": -4.371139e-8,
      "x": 0,
      "y": 1,
      "z": 0
    },
    "color": -11439553,
    "materialId": 0,
    "type": "1x1Plate",
    "usingNewColor": true,
    "user": "e745848173210df6969de43cb63418a5"
  },
  {
    "pos": {
      "x": 0.03171884,
      "y": 0.734996,
      "z": 3.287924
    },
    "rot": {
      "w": -0.7071068,
      "x": 0,
      "y": -0.7071069,
      "z": 0
    },
    "color": -11439553,
    "materialId": 0,
    "type": "2x2CornerPlate",
    "usingNewColor": true,
    "user": "e745848173210df6969de43cb63418a5"
  },
  {
    "pos": {
      "x": 0.115831,
      "y": 0.9586399,
      "z": 2.783375
    },
    "rot": {
      "w": -0.7071065,
      "x": 0,
      "y": -0.7071072,
      "z": 0
    },
    "color": -8299003,
    "materialId": 0,
    "type": "1x2",
    "usingNewColor": true,
    "user": "a56d3b43eae48f9b33be2485279ee312"
  },
  {
    "pos": {
      "x": -0.05239382,
      "y": 0.8915039,
      "z": 3.708488
    },
    "rot": {
      "w": 1.311342e-7,
      "x": 0,
      "y": -1,
      "z": 0
    },
    "color": -8299003,
    "materialId": 0,
    "type": "1x1",
    "usingNewColor": true,
    "user": "a56d3b43eae48f9b33be2485279ee312"
  },
  {
    "pos": {
      "x": 0.05975582,
      "y": 0.734996,
      "z": 2.643061
    },
    "rot": {
      "w": -1,
      "x": 0,
      "y": -8.742278e-8,
      "z": 0
    },
    "color": -2619344,
    "materialId": 0,
    "type": "FlatPlant",
    "usingNewColor": true,
    "user": "e745848173210df6969de43cb63418a5"
  },
  {
    "pos": {
      "x": -0.3888453,
      "y": 0.8915039,
      "z": 3.708489
    },
    "rot": {
      "w": 1.311342e-7,
      "x": 0,
      "y": -1,
      "z": 0
    },
    "color": -8299003,
    "materialId": 0,
    "type": "1x1",
    "usingNewColor": true,
    "user": "a56d3b43eae48f9b33be2485279ee312"
  },
  {
    "pos": {
      "x": 0.115831,
      "y": 1.025776,
      "z": 3.652415
    },
    "rot": {
      "w": 0.7071069,
      "x": 0,
      "y": -0.7071067,
      "z": 0
    },
    "color": -8299003,
    "materialId": 0,
    "type": "1x1",
    "usingNewColor": true,
    "user": "a56d3b43eae48f9b33be2485279ee312"
  },
  {
    "pos": {
      "x": 0.03171806,
      "y": 0.734996,
      "z": 3.568301
    },
    "rot": {
      "w": -0.7071068,
      "x": 0,
      "y": -0.7071069,
      "z": 0
    },
    "color": -11439553,
    "materialId": 0,
    "type": "2x4Plate",
    "usingNewColor": true,
    "user": "e745848173210df6969de43cb63418a5"
  },
  {
    "pos": {
      "x": -0.8652827,
      "y": 0.757496,
      "z": -1.362338
    },
    "rot": {
      "w": -0.7071069,
      "x": 0,
      "y": 0.7071067,
      "z": 0
    },
    "color": -3815995,
    "materialId": 0,
    "type": "2x4Plate",
    "usingNewColor": true,
    "user": "e745848173210df6969de43cb63418a5"
  },
  {
    "pos": {
      "x": -0.1925822,
      "y": 0.734996,
      "z": 3.315962
    },
    "rot": {
      "w": -4.371139e-8,
      "x": 0,
      "y": 1,
      "z": 0
    },
    "color": -11439553,
    "materialId": 0,
    "type": "1x2Plate",
    "usingNewColor": true,
    "user": "e745848173210df6969de43cb63418a5"
  },
  {
    "pos": {
      "x": -0.2206198,
      "y": 0.8915039,
      "z": 2.783375
    },
    "rot": {
      "w": -0.7071066,
      "x": 0,
      "y": -0.7071071,
      "z": 0
    },
    "color": -8299003,
    "materialId": 0,
    "type": "1x2",
    "usingNewColor": true,
    "user": "a56d3b43eae48f9b33be2485279ee312"
  },
  {
    "pos": {
      "x": -0.2206198,
      "y": 0.8243679,
      "z": 2.783374
    },
    "rot": {
      "w": -0.7071067,
      "x": 0,
      "y": -0.7071069,
      "z": 0
    },
    "color": -8299003,
    "materialId": 0,
    "type": "1x2",
    "usingNewColor": true,
    "user": "a56d3b43eae48f9b33be2485279ee312"
  },
  {
    "pos": {
      "x": -0.1083946,
      "y": 1.003504,
      "z": 2.699387
    },
    "rot": {
      "w": -1,
      "x": 0,
      "y": -8.702397e-7,
      "z": 0
    },
    "color": -12991188,
    "materialId": 0,
    "type": "1x1Plate",
    "usingNewColor": true,
    "user": "a56d3b43eae48f9b33be2485279ee312"
  },
  {
    "pos": {
      "x": 0.115831,
      "y": 0.9586399,
      "z": 2.895398
    },
    "rot": {
      "w": 0.7071069,
      "x": 0,
      "y": -0.7071067,
      "z": 0
    },
    "color": -8299003,
    "materialId": 0,
    "type": "1x2",
    "usingNewColor": true,
    "user": "a56d3b43eae48f9b33be2485279ee312"
  },
  {
    "pos": {
      "x": -0.1365067,
      "y": 0.8915039,
      "z": 3.708488
    },
    "rot": {
      "w": 1.311342e-7,
      "x": 0,
      "y": -1,
      "z": 0
    },
    "color": -7703232,
    "materialId": 0,
    "type": "1x2",
    "usingNewColor": true,
    "user": "a56d3b43eae48f9b33be2485279ee312"
  },
  {
    "pos": {
      "x": -0.3047318,
      "y": 1.025776,
      "z": 3.708489
    },
    "rot": {
      "w": 1.311342e-7,
      "x": 0,
      "y": -1,
      "z": 0
    },
    "color": -8299003,
    "materialId": 0,
    "type": "1x4Arch",
    "usingNewColor": true,
    "user": "a56d3b43eae48f9b33be2485279ee312"
  },
  {
    "pos": {
      "x": 0.115831,
      "y": 0.8243679,
      "z": 2.895398
    },
    "rot": {
      "w": 0.7071069,
      "x": 0,
      "y": -0.7071067,
      "z": 0
    },
    "color": -8299003,
    "materialId": 0,
    "type": "1x2",
    "usingNewColor": true,
    "user": "a56d3b43eae48f9b33be2485279ee312"
  },
  {
    "pos": {
      "x": -0.276695,
      "y": 0.734996,
      "z": 2.923436
    },
    "rot": {
      "w": -0.7071068,
      "x": 0,
      "y": -0.7071069,
      "z": 0
    },
    "color": -11439553,
    "materialId": 0,
    "type": "1x3Plate",
    "usingNewColor": true,
    "user": "e745848173210df6969de43cb63418a5"
  },
  {
    "pos": {
      "x": -0.3888453,
      "y": 0.8243679,
      "z": 3.708489
    },
    "rot": {
      "w": 4.371139e-8,
      "x": 0,
      "y": -1,
      "z": 0
    },
    "color": -8299003,
    "materialId": 0,
    "type": "1x1",
    "usingNewColor": true,
    "user": "a56d3b43eae48f9b33be2485279ee312"
  },
  {
    "pos": {
      "x": 0.2119699,
      "y": 0.9183721,
      "z": 3.259588
    },
    "rot": {
      "w": -0.5000001,
      "x": 0.5000001,
      "y": 0.4999999,
      "z": 0.5
    },
    "color": -12991188,
    "materialId": 0,
    "type": "1x1RoundPlate",
    "usingNewColor": true,
    "user": "a56d3b43eae48f9b33be2485279ee312"
  },
  {
    "pos": {
      "x": 0.115831,
      "y": 0.8915039,
      "z": 2.895398
    },
    "rot": {
      "w": 0.7071069,
      "x": 0,
      "y": -0.7071067,
      "z": 0
    },
    "color": -8299003,
    "materialId": 0,
    "type": "1x2",
    "usingNewColor": true,
    "user": "a56d3b43eae48f9b33be2485279ee312"
  },
  {
    "pos": {
      "x": -0.8652835,
      "y": 0.757496,
      "z": -1.642714
    },
    "rot": {
      "w": -0.7071069,
      "x": 0,
      "y": 0.7071067,
      "z": 0
    },
    "color": -3815995,
    "materialId": 0,
    "type": "2x2Plate",
    "usingNewColor": true,
    "user": "e745848173210df6969de43cb63418a5"
  },
  {
    "pos": {
      "x": -0.3886445,
      "y": 0.8243679,
      "z": 2.783375
    },
    "rot": {
      "w": -0.7071067,
      "x": 0,
      "y": -0.7071069,
      "z": 0
    },
    "color": -8299003,
    "materialId": 0,
    "type": "1x2",
    "usingNewColor": true,
    "user": "a56d3b43eae48f9b33be2485279ee312"
  },
  {
    "pos": {
      "x": 0.3401316,
      "y": 0.757232,
      "z": -2.624029
    },
    "rot": {
      "w": -4.371139e-8,
      "x": 0,
      "y": 1,
      "z": 0
    },
    "color": -11439553,
    "materialId": 0,
    "type": "1x1",
    "usingNewColor": true,
    "user": "e745848173210df6969de43cb63418a5"
  },
  {
    "pos": {
      "x": -0.697259,
      "y": 0.734996,
      "z": -1.642714
    },
    "rot": {
      "w": -4.371139e-8,
      "x": 0,
      "y": 1,
      "z": 0
    },
    "color": -14252289,
    "materialId": 0,
    "type": "2x8Plate",
    "usingNewColor": true,
    "user": "e745848173210df6969de43cb63418a5"
  },
  {
    "pos": {
      "x": 0.3401316,
      "y": 0.757232,
      "z": -2.792255
    },
    "rot": {
      "w": -0.7071068,
      "x": 0,
      "y": -0.7071069,
      "z": 0
    },
    "color": -11439553,
    "materialId": 0,
    "type": "1x1",
    "usingNewColor": true,
    "user": "e745848173210df6969de43cb63418a5"
  },
  {
    "pos": {
      "x": 0.115831,
      "y": 0.802132,
      "z": 2.699136
    },
    "rot": {
      "w": -1,
      "x": 0,
      "y": -1.748456e-7,
      "z": 0
    },
    "color": -2571834,
    "materialId": 0,
    "type": "FlatPlant",
    "usingNewColor": true,
    "user": "e745848173210df6969de43cb63418a5"
  },
  {
    "pos": {
      "x": -0.3886445,
      "y": 0.8915039,
      "z": 2.783375
    },
    "rot": {
      "w": -0.7071066,
      "x": 0,
      "y": -0.7071071,
      "z": 0
    },
    "color": -8299003,
    "materialId": 0,
    "type": "1x2",
    "usingNewColor": true,
    "user": "a56d3b43eae48f9b33be2485279ee312"
  },
  {
    "pos": {
      "x": -0.3888453,
      "y": 0.757232,
      "z": 3.708489
    },
    "rot": {
      "w": -0.7071067,
      "x": 0,
      "y": -0.7071069,
      "z": 0
    },
    "color": -8299003,
    "materialId": 0,
    "type": "1x1",
    "usingNewColor": true,
    "user": "a56d3b43eae48f9b33be2485279ee312"
  },
  {
    "pos": {
      "x": 0.05975582,
      "y": 0.734996,
      "z": 3.315962
    },
    "rot": {
      "w": -0.7071068,
      "x": 0,
      "y": -0.7071069,
      "z": 0
    },
    "color": -11439553,
    "materialId": 0,
    "type": "1x1Plate",
    "usingNewColor": true,
    "user": "e745848173210df6969de43cb63418a5"
  },
  {
    "pos": {
      "x": 0.115831,
      "y": 0.8243679,
      "z": 3.680452
    },
    "rot": {
      "w": 0.7071069,
      "x": 0,
      "y": -0.7071067,
      "z": 0
    },
    "color": -8299003,
    "materialId": 0,
    "type": "1x2",
    "usingNewColor": true,
    "user": "e745848173210df6969de43cb63418a5"
  },
  {
    "pos": {
      "x": -0.3048574,
      "y": 0.8582399,
      "z": 2.755336
    },
    "rot": {
      "w": 5.205485e-7,
      "x": 0,
      "y": -1,
      "z": 0
    },
    "color": -8299003,
    "materialId": 0,
    "type": "1x2Window",
    "usingNewColor": true,
    "user": "a56d3b43eae48f9b33be2485279ee312"
  },
  {
    "pos": {
      "x": -0.1083946,
      "y": 1.026004,
      "z": 2.699387
    },
    "rot": {
      "w": -1,
      "x": 0,
      "y": -9.576625e-7,
      "z": 0
    },
    "color": -12991188,
    "materialId": 0,
    "type": "ThreeLeafedPlant",
    "usingNewColor": true,
    "user": "a56d3b43eae48f9b33be2485279ee312"
  },
  {
    "pos": {
      "x": -0.1364321,
      "y": 1.070676,
      "z": 2.811286
    },
    "rot": {
      "w": -1,
      "x": 0,
      "y": -6.079713e-7,
      "z": 0
    },
    "color": -8299003,
    "materialId": 0,
    "type": "1x4Plate",
    "usingNewColor": true,
    "user": "a56d3b43eae48f9b33be2485279ee312"
  },
  {
    "pos": {
      "x": -0.3047328,
      "y": 0.734996,
      "z": 3.568301
    },
    "rot": {
      "w": -0.7071068,
      "x": 0,
      "y": -0.7071069,
      "z": 0
    },
    "color": -11439553,
    "materialId": 0,
    "type": "2x4Plate",
    "usingNewColor": true,
    "user": "e745848173210df6969de43cb63418a5"
  },
  {
    "pos": {
      "x": -0.2766947,
      "y": 0.802132,
      "z": 3.708488
    },
    "rot": {
      "w": -1,
      "x": 0,
      "y": -8.742278e-8,
      "z": 0
    },
    "color": -2571834,
    "materialId": 0,
    "type": "FlatPlant",
    "usingNewColor": true,
    "user": "e745848173210df6969de43cb63418a5"
  },
  {
    "pos": {
      "x": -0.8933203,
      "y": 0.802232,
      "z": -1.530565
    },
    "rot": {
      "w": -0.7071068,
      "x": 0,
      "y": -0.7071069,
      "z": 0
    },
    "color": -3815995,
    "materialId": 0,
    "type": "1x6",
    "usingNewColor": true,
    "user": "e745848173210df6969de43cb63418a5"
  },
  {
    "pos": {
      "x": -0.3327702,
      "y": 0.734996,
      "z": 3.119701
    },
    "rot": {
      "w": -0.7071068,
      "x": 0,
      "y": -0.7071069,
      "z": 0
    },
    "color": -11439553,
    "materialId": 0,
    "type": "1x8Plate",
    "usingNewColor": true,
    "user": "e745848173210df6969de43cb63418a5"
  },
  {
    "pos": {
      "x": -0.2206198,
      "y": 0.9586399,
      "z": 2.783374
    },
    "rot": {
      "w": -0.7071071,
      "x": 0,
      "y": 0.7071065,
      "z": 0
    },
    "color": -8299003,
    "materialId": 0,
    "type": "1x2",
    "usingNewColor": true,
    "user": "a56d3b43eae48f9b33be2485279ee312"
  },
  {
    "pos": {
      "x": -0.8652838,
      "y": 0.757496,
      "z": -1.530563
    },
    "rot": {
      "w": -0.7071069,
      "x": 0,
      "y": 0.7071067,
      "z": 0
    },
    "color": -3815995,
    "materialId": 0,
    "type": "2x2Plate",
    "usingNewColor": true,
    "user": "e745848173210df6969de43cb63418a5"
  },
  {
    "pos": {
      "x": -0.2206191,
      "y": 0.9586399,
      "z": 3.708489
    },
    "rot": {
      "w": 1.311342e-7,
      "x": 0,
      "y": -1,
      "z": 0
    },
    "color": -8299003,
    "materialId": 0,
    "type": "1x1",
    "usingNewColor": true,
    "user": "a56d3b43eae48f9b33be2485279ee312"
  },
  {
    "pos": {
      "x": 0.03181864,
      "y": 0.757232,
      "z": 2.783311
    },
    "rot": {
      "w": -1,
      "x": 0,
      "y": -8.742278e-8,
      "z": 0
    },
    "color": -8299003,
    "materialId": 0,
    "type": "4x2",
    "usingNewColor": true,
    "user": "a56d3b43eae48f9b33be2485279ee312"
  },
  {
    "pos": {
      "x": 0.115831,
      "y": 1.025776,
      "z": 2.895398
    },
    "rot": {
      "w": 0.7071069,
      "x": 0,
      "y": -0.7071067,
      "z": 0
    },
    "color": -8299003,
    "materialId": 0,
    "type": "1x2",
    "usingNewColor": true,
    "user": "a56d3b43eae48f9b33be2485279ee312"
  },
  {
    "pos": {
      "x": -0.05239382,
      "y": 0.8243679,
      "z": 3.708488
    },
    "rot": {
      "w": 1.311342e-7,
      "x": 0,
      "y": -1,
      "z": 0
    },
    "color": -8299003,
    "materialId": 0,
    "type": "1x1",
    "usingNewColor": true,
    "user": "a56d3b43eae48f9b33be2485279ee312"
  },
  {
    "pos": {
      "x": -0.1925824,
      "y": 0.734996,
      "z": 3.175775
    },
    "rot": {
      "w": -0.7071068,
      "x": 0,
      "y": -0.7071069,
      "z": 0
    },
    "color": -11439553,
    "materialId": 0,
    "type": "2x4Plate",
    "usingNewColor": true,
    "user": "e745848173210df6969de43cb63418a5"
  },
  {
    "pos": {
      "x": -0.1644697,
      "y": 1.003504,
      "z": 2.699388
    },
    "rot": {
      "w": -1,
      "x": 0,
      "y": -8.702397e-7,
      "z": 0
    },
    "color": -12991188,
    "materialId": 0,
    "type": "FlatPlant",
    "usingNewColor": true,
    "user": "a56d3b43eae48f9b33be2485279ee312"
  },
  {
    "pos": {
      "x": -0.6972597,
      "y": 0.734996,
      "z": -1.530563
    },
    "rot": {
      "w": -4.371139e-8,
      "x": 0,
      "y": 1,
      "z": 0
    },
    "color": -14252289,
    "materialId": 0,
    "type": "2x8Plate",
    "usingNewColor": true,
    "user": "e745848173210df6969de43cb63418a5"
  },
  {
    "pos": {
      "x": 0.05975584,
      "y": 0.802132,
      "z": 2.699136
    },
    "rot": {
      "w": -1,
      "x": 0,
      "y": -1.748456e-7,
      "z": 0
    },
    "color": -2571834,
    "materialId": 0,
    "type": "FlatPlant",
    "usingNewColor": true,
    "user": "e745848173210df6969de43cb63418a5"
  },
  {
    "pos": {
      "x": -0.3889707,
      "y": 0.9586399,
      "z": 2.783375
    },
    "rot": {
      "w": -0.7071064,
      "x": 0,
      "y": -0.7071072,
      "z": 0
    },
    "color": -8299003,
    "materialId": 0,
    "type": "1x2",
    "usingNewColor": true,
    "user": "a56d3b43eae48f9b33be2485279ee312"
  },
  {
    "pos": {
      "x": 0.03171796,
      "y": 0.734996,
      "z": 3.147737
    },
    "rot": {
      "w": -0.7071068,
      "x": 0,
      "y": -0.7071069,
      "z": 0
    },
    "color": -11439553,
    "materialId": 0,
    "type": "2x3Plate",
    "usingNewColor": true,
    "user": "e745848173210df6969de43cb63418a5"
  },
  {
    "pos": {
      "x": -0.05231936,
      "y": 0.9586399,
      "z": 2.783375
    },
    "rot": {
      "w": -0.7071064,
      "x": 0,
      "y": -0.7071072,
      "z": 0
    },
    "color": -8299003,
    "materialId": 0,
    "type": "1x2",
    "usingNewColor": true,
    "user": "a56d3b43eae48f9b33be2485279ee312"
  },
  {
    "pos": {
      "x": -0.3328956,
      "y": 1.025776,
      "z": 2.783311
    },
    "rot": {
      "w": 1,
      "x": 0,
      "y": 5.205485e-7,
      "z": 0
    },
    "color": -8299003,
    "materialId": 0,
    "type": "2x3",
    "usingNewColor": true,
    "user": "a56d3b43eae48f9b33be2485279ee312"
  },
  {
    "pos": {
      "x": -0.08043228,
      "y": 0.734996,
      "z": 3.568301
    },
    "rot": {
      "w": -0.7071068,
      "x": 0,
      "y": -0.7071069,
      "z": 0
    },
    "color": -11439553,
    "materialId": 0,
    "type": "2x4Plate",
    "usingNewColor": true,
    "user": "e745848173210df6969de43cb63418a5"
  },
  {
    "pos": {
      "x": 0.003755789,
      "y": 1.025776,
      "z": 2.783311
    },
    "rot": {
      "w": 1,
      "x": 0,
      "y": 5.205485e-7,
      "z": 0
    },
    "color": -8299003,
    "materialId": 0,
    "type": "2x3",
    "usingNewColor": true,
    "user": "a56d3b43eae48f9b33be2485279ee312"
  },
  {
    "pos": {
      "x": -0.3327702,
      "y": 0.734996,
      "z": 2.643061
    },
    "rot": {
      "w": -0.7071069,
      "x": 0,
      "y": 0.7071068,
      "z": 0
    },
    "color": -3589831,
    "materialId": 0,
    "type": "FlatPlant",
    "usingNewColor": true,
    "user": "e745848173210df6969de43cb63418a5"
  },
  {
    "pos": {
      "x": 0.5644321,
      "y": 0.757232,
      "z": -2.73618
    },
    "rot": {
      "w": -4.371139e-8,
      "x": 0,
      "y": 1,
      "z": 0
    },
    "color": -11439553,
    "materialId": 0,
    "type": "1x1",
    "usingNewColor": true,
    "user": "e745848173210df6969de43cb63418a5"
  },
  {
    "pos": {
      "x": 0.08779341,
      "y": 0.757232,
      "z": 2.699136
    },
    "rot": {
      "w": -1,
      "x": 0,
      "y": -8.742278e-8,
      "z": 0
    },
    "color": -11439553,
    "materialId": 0,
    "type": "1x2",
    "usingNewColor": true,
    "user": "e745848173210df6969de43cb63418a5"
  },
  {
    "pos": {
      "x": -0.1364321,
      "y": 1.02574,
      "z": 2.783312
    },
    "rot": {
      "w": -1,
      "x": 0,
      "y": -6.953941e-7,
      "z": 0
    },
    "color": -8299003,
    "materialId": 0,
    "type": "2x2",
    "usingNewColor": true,
    "user": "a56d3b43eae48f9b33be2485279ee312"
  },
  {
    "pos": {
      "x": 0.115831,
      "y": 0.734996,
      "z": 2.643061
    },
    "rot": {
      "w": -1,
      "x": 0,
      "y": -8.742278e-8,
      "z": 0
    },
    "color": -2661790,
    "materialId": 0,
    "type": "FlatPlant",
    "usingNewColor": true,
    "user": "a56d3b43eae48f9b33be2485279ee312"
  },
  {
    "pos": {
      "x": -0.1365068,
      "y": 0.8243679,
      "z": 3.708488
    },
    "rot": {
      "w": 1.311342e-7,
      "x": 0,
      "y": -1,
      "z": 0
    },
    "color": -7703232,
    "materialId": 0,
    "type": "1x2",
    "usingNewColor": true,
    "user": "a56d3b43eae48f9b33be2485279ee312"
  },
  {
    "pos": {
      "x": 0.6765823,
      "y": 0.757232,
      "z": -2.73618
    },
    "rot": {
      "w": -0.7071068,
      "x": 0,
      "y": -0.7071069,
      "z": 0
    },
    "color": -11439553,
    "materialId": 0,
    "type": "1x3",
    "usingNewColor": true,
    "user": "e745848173210df6969de43cb63418a5"
  },
  {
    "pos": {
      "x": 0.1717809,
      "y": 0.8692679,
      "z": 3.287625
    },
    "rot": {
      "w": -0.7071069,
      "x": 0,
      "y": 0.7071066,
      "z": 0
    },
    "color": -12991188,
    "materialId": 0,
    "type": "1x2Plate",
    "usingNewColor": true,
    "user": "a56d3b43eae48f9b33be2485279ee312"
  },
  {
    "pos": {
      "x": 0.5644321,
      "y": 0.757232,
      "z": -2.680104
    },
    "rot": {
      "w": -4.371139e-8,
      "x": 0,
      "y": 1,
      "z": 0
    },
    "color": -11439553,
    "materialId": 0,
    "type": "1x1",
    "usingNewColor": true,
    "user": "e745848173210df6969de43cb63418a5"
  },
  {
    "pos": {
      "x": 0.115831,
      "y": 0.8915039,
      "z": 3.568302
    },
    "rot": {
      "w": 0.7071069,
      "x": 0,
      "y": -0.7071067,
      "z": 0
    },
    "color": -8299003,
    "materialId": 0,
    "type": "1x6",
    "usingNewColor": true,
    "user": "a56d3b43eae48f9b33be2485279ee312"
  },
  {
    "pos": {
      "x": 0.115831,
      "y": 0.757232,
      "z": 3.119699
    },
    "rot": {
      "w": -0.7071069,
      "x": 0,
      "y": 0.7071068,
      "z": 0
    },
    "color": -8299003,
    "materialId": 0,
    "type": "1x10",
    "usingNewColor": true,
    "user": "a56d3b43eae48f9b33be2485279ee312"
  },
  {
    "pos": {
      "x": 0.6205072,
      "y": 0.757232,
      "z": -2.73618
    },
    "rot": {
      "w": -4.371139e-8,
      "x": 0,
      "y": 1,
      "z": 0
    },
    "color": -11439553,
    "materialId": 0,
    "type": "1x1",
    "usingNewColor": true,
    "user": "e745848173210df6969de43cb63418a5"
  },
  {
    "pos": {
      "x": 0.1717809,
      "y": 0.958904,
      "z": 3.259588
    },
    "rot": {
      "w": -0.7071069,
      "x": 0,
      "y": 0.7071066,
      "z": 0
    },
    "color": -12991188,
    "materialId": 0,
    "type": "FlatPlant",
    "usingNewColor": true,
    "user": "a56d3b43eae48f9b33be2485279ee312"
  },
  {
    "pos": {
      "x": -0.6972588,
      "y": 0.734996,
      "z": -1.194113
    },
    "rot": {
      "w": -4.371139e-8,
      "x": 0,
      "y": 1,
      "z": 0
    },
    "color": -14252289,
    "materialId": 0,
    "type": "2x8Plate",
    "usingNewColor": true,
    "user": "e745848173210df6969de43cb63418a5"
  },
  {
    "pos": {
      "x": -0.6972594,
      "y": 0.734996,
      "z": -1.081962
    },
    "rot": {
      "w": -4.371139e-8,
      "x": 0,
      "y": 1,
      "z": 0
    },
    "color": -14252289,
    "materialId": 0,
    "type": "2x8Plate",
    "usingNewColor": true,
    "user": "e745848173210df6969de43cb63418a5"
  },
  {
    "pos": {
      "x": 0.5644321,
      "y": 0.757232,
      "z": -2.792255
    },
    "rot": {
      "w": -4.371139e-8,
      "x": 0,
      "y": 1,
      "z": 0
    },
    "color": -11439553,
    "materialId": 0,
    "type": "1x1",
    "usingNewColor": true,
    "user": "e745848173210df6969de43cb63418a5"
  },
  {
    "pos": {
      "x": -0.8652835,
      "y": 0.757496,
      "z": -1.138038
    },
    "rot": {
      "w": -0.7071069,
      "x": 0,
      "y": 0.7071067,
      "z": 0
    },
    "color": -3815995,
    "materialId": 0,
    "type": "2x4Plate",
    "usingNewColor": true,
    "user": "e745848173210df6969de43cb63418a5"
  },
  {
    "pos": {
      "x": -0.7813718,
      "y": 0.757496,
      "z": -1.586635
    },
    "rot": {
      "w": -0.7071068,
      "x": 0,
      "y": -0.7071069,
      "z": 0
    },
    "color": -3815995,
    "materialId": 0,
    "type": "1x4Plate",
    "usingNewColor": true,
    "user": "e745848173210df6969de43cb63418a5"
  },
  {
    "pos": {
      "x": -0.1925826,
      "y": 0.734996,
      "z": 2.951474
    },
    "rot": {
      "w": -0.7071068,
      "x": 0,
      "y": -0.7071069,
      "z": 0
    },
    "color": -11439553,
    "materialId": 0,
    "type": "2x4Plate",
    "usingNewColor": true,
    "user": "e745848173210df6969de43cb63418a5"
  },
  {
    "pos": {
      "x": -0.2206198,
      "y": 1.025776,
      "z": 2.783374
    },
    "rot": {
      "w": -0.7071064,
      "x": 0,
      "y": -0.7071072,
      "z": 0
    },
    "color": -8299003,
    "materialId": 0,
    "type": "1x2",
    "usingNewColor": true,
    "user": "a56d3b43eae48f9b33be2485279ee312"
  },
  {
    "pos": {
      "x": 0.03171834,
      "y": 1.025776,
      "z": 3.70849
    },
    "rot": {
      "w": 1,
      "x": 0,
      "y": 4.371139e-8,
      "z": 0
    },
    "color": -8299003,
    "materialId": 0,
    "type": "1x4Arch",
    "usingNewColor": true,
    "user": "a56d3b43eae48f9b33be2485279ee312"
  },
  {
    "pos": {
      "x": -0.05239698,
      "y": 0.9586399,
      "z": 3.70849
    },
    "rot": {
      "w": 1.311342e-7,
      "x": 0,
      "y": -1,
      "z": 0
    },
    "color": -8299003,
    "materialId": 0,
    "type": "1x1",
    "usingNewColor": true,
    "user": "a56d3b43eae48f9b33be2485279ee312"
  },
  {
    "pos": {
      "x": -0.08043221,
      "y": 0.734996,
      "z": 3.23185
    },
    "rot": {
      "w": -0.7071068,
      "x": 0,
      "y": -0.7071069,
      "z": 0
    },
    "color": -11439553,
    "materialId": 0,
    "type": "2x4Plate",
    "usingNewColor": true,
    "user": "e745848173210df6969de43cb63418a5"
  },
  {
    "pos": {
      "x": -0.3888445,
      "y": 0.9586399,
      "z": 3.708489
    },
    "rot": {
      "w": 1.311342e-7,
      "x": 0,
      "y": -1,
      "z": 0
    },
    "color": -8299003,
    "materialId": 0,
    "type": "1x1",
    "usingNewColor": true,
    "user": "a56d3b43eae48f9b33be2485279ee312"
  },
  {
    "pos": {
      "x": 0.115831,
      "y": 1.025776,
      "z": 2.783375
    },
    "rot": {
      "w": -0.7071064,
      "x": 0,
      "y": -0.7071073,
      "z": 0
    },
    "color": -8299003,
    "materialId": 0,
    "type": "1x2",
    "usingNewColor": true,
    "user": "a56d3b43eae48f9b33be2485279ee312"
  },
  {
    "pos": {
      "x": 0.03171799,
      "y": 0.734996,
      "z": 2.951474
    },
    "rot": {
      "w": -0.7071068,
      "x": 0,
      "y": -0.7071069,
      "z": 0
    },
    "color": -11439553,
    "materialId": 0,
    "type": "2x4Plate",
    "usingNewColor": true,
    "user": "e745848173210df6969de43cb63418a5"
  },
  {
    "pos": {
      "x": -0.3888453,
      "y": 0.802132,
      "z": 2.699136
    },
    "rot": {
      "w": -1,
      "x": 0,
      "y": -1.748456e-7,
      "z": 0
    },
    "color": -2571834,
    "materialId": 0,
    "type": "FlatPlant",
    "usingNewColor": true,
    "user": "e745848173210df6969de43cb63418a5"
  },
  {
    "pos": {
      "x": -0.3888453,
      "y": 0.734996,
      "z": 2.643061
    },
    "rot": {
      "w": -1,
      "x": 0,
      "y": -8.742278e-8,
      "z": 0
    },
    "color": -2619344,
    "materialId": 0,
    "type": "FlatPlant",
    "usingNewColor": true,
    "user": "e745848173210df6969de43cb63418a5"
  },
  {
    "pos": {
      "x": -0.2206196,
      "y": 0.8915039,
      "z": 3.708488
    },
    "rot": {
      "w": 1.311342e-7,
      "x": 0,
      "y": -1,
      "z": 0
    },
    "color": -8299003,
    "materialId": 0,
    "type": "1x1",
    "usingNewColor": true,
    "user": "a56d3b43eae48f9b33be2485279ee312"
  },
  {
    "pos": {
      "x": 0.1717809,
      "y": 0.958904,
      "z": 3.315663
    },
    "rot": {
      "w": -0.7071069,
      "x": 0,
      "y": 0.7071066,
      "z": 0
    },
    "color": -12991188,
    "materialId": 0,
    "type": "ThreeLeafedPlant",
    "usingNewColor": true,
    "user": "a56d3b43eae48f9b33be2485279ee312"
  },
  {
    "pos": {
      "x": 0.115831,
      "y": 0.8915039,
      "z": 2.783374
    },
    "rot": {
      "w": -0.7071066,
      "x": 0,
      "y": -0.7071071,
      "z": 0
    },
    "color": -8299003,
    "materialId": 0,
    "type": "1x2",
    "usingNewColor": true,
    "user": "a56d3b43eae48f9b33be2485279ee312"
  },
  {
    "pos": {
      "x": -0.4168827,
      "y": 0.734996,
      "z": -1.138038
    },
    "rot": {
      "w": -0.7071069,
      "x": 0,
      "y": 0.7071068,
      "z": 0
    },
    "color": -14252289,
    "materialId": 0,
    "type": "2x4Plate",
    "usingNewColor": true,
    "user": "e745848173210df6969de43cb63418a5"
  },
  {
    "pos": {
      "x": -0.02435697,
      "y": 0.734996,
      "z": 3.400075
    },
    "rot": {
      "w": -1,
      "x": 0,
      "y": -8.742278e-8,
      "z": 0
    },
    "color": -11439553,
    "materialId": 0,
    "type": "2x4Plate",
    "usingNewColor": true,
    "user": "e745848173210df6969de43cb63418a5"
  },
  {
    "pos": {
      "x": -0.05219375,
      "y": 0.8915039,
      "z": 2.783248
    },
    "rot": {
      "w": 0.7071069,
      "x": 0,
      "y": -0.7071067,
      "z": 0
    },
    "color": -8299003,
    "materialId": 0,
    "type": "1x2",
    "usingNewColor": true,
    "user": "a56d3b43eae48f9b33be2485279ee312"
  },
  {
    "pos": {
      "x": -0.136432,
      "y": 1.070676,
      "z": 2.755337
    },
    "rot": {
      "w": -1,
      "x": 0,
      "y": -6.079713e-7,
      "z": 0
    },
    "color": -8299003,
    "materialId": 0,
    "type": "1x4Plate",
    "usingNewColor": true,
    "user": "a56d3b43eae48f9b33be2485279ee312"
  },
  {
    "pos": {
      "x": -0.2765945,
      "y": 0.802132,
      "z": 2.811286
    },
    "rot": {
      "w": -1.311342e-7,
      "x": 0,
      "y": 1,
      "z": 0
    },
    "color": -2661790,
    "materialId": 0,
    "type": "ThreeLeafedPlant",
    "usingNewColor": true,
    "user": "a56d3b43eae48f9b33be2485279ee312"
  },
  {
    "pos": {
      "x": -0.6972586,
      "y": 0.734996,
      "z": -1.418414
    },
    "rot": {
      "w": -1,
      "x": 0,
      "y": -8.742278e-8,
      "z": 0
    },
    "color": -14252289,
    "materialId": 0,
    "type": "2x8Plate",
    "usingNewColor": true,
    "user": "e745848173210df6969de43cb63418a5"
  },
  {
    "pos": {
      "x": 0.4522819,
      "y": 0.757232,
      "z": -2.792255
    },
    "rot": {
      "w": -4.371139e-8,
      "x": 0,
      "y": 1,
      "z": 0
    },
    "color": -11439553,
    "materialId": 0,
    "type": "1x1",
    "usingNewColor": true,
    "user": "e745848173210df6969de43cb63418a5"
  },
  {
    "pos": {
      "x": -0.3049207,
      "y": 0.9586399,
      "z": 2.727299
    },
    "rot": {
      "w": -0.7071072,
      "x": 0,
      "y": 0.7071064,
      "z": 0
    },
    "color": -7703232,
    "materialId": 0,
    "type": "2x2Slope",
    "usingNewColor": true,
    "user": "a56d3b43eae48f9b33be2485279ee312"
  },
  {
    "pos": {
      "x": 0.03173056,
      "y": 0.9586399,
      "z": 2.727299
    },
    "rot": {
      "w": -0.7071072,
      "x": 0,
      "y": 0.7071064,
      "z": 0
    },
    "color": -7703232,
    "materialId": 0,
    "type": "2x2Slope",
    "usingNewColor": true,
    "user": "a56d3b43eae48f9b33be2485279ee312"
  },
  {
    "pos": {
      "x": -0.6972594,
      "y": 0.734996,
      "z": -1.306263
    },
    "rot": {
      "w": -4.371139e-8,
      "x": 0,
      "y": 1,
      "z": 0
    },
    "color": -14252289,
    "materialId": 0,
    "type": "2x8Plate",
    "usingNewColor": true,
    "user": "e745848173210df6969de43cb63418a5"
  },
  {
    "pos": {
      "x": 0.4522819,
      "y": 0.757232,
      "z": -2.624029
    },
    "rot": {
      "w": -0.7071069,
      "x": 0,
      "y": 0.7071068,
      "z": 0
    },
    "color": -11439553,
    "materialId": 0,
    "type": "1x1",
    "usingNewColor": true,
    "user": "e745848173210df6969de43cb63418a5"
  },
  {
    "pos": {
      "x": 0.115831,
      "y": 0.9586399,
      "z": 3.568303
    },
    "rot": {
      "w": 0.7071069,
      "x": 0,
      "y": -0.7071067,
      "z": 0
    },
    "color": -8299003,
    "materialId": 0,
    "type": "1x6",
    "usingNewColor": true,
    "user": "a56d3b43eae48f9b33be2485279ee312"
  },
  {
    "pos": {
      "x": -0.276695,
      "y": 0.734996,
      "z": 3.175777
    },
    "rot": {
      "w": -0.7071068,
      "x": 0,
      "y": -0.7071069,
      "z": 0
    },
    "color": -11439553,
    "materialId": 0,
    "type": "1x6Plate",
    "usingNewColor": true,
    "user": "e745848173210df6969de43cb63418a5"
  },
  {
    "pos": {
      "x": -0.3327701,
      "y": 0.802132,
      "z": 2.699136
    },
    "rot": {
      "w": -1,
      "x": 0,
      "y": -1.748456e-7,
      "z": 0
    },
    "color": -2661790,
    "materialId": 0,
    "type": "FlatPlant",
    "usingNewColor": true,
    "user": "a56d3b43eae48f9b33be2485279ee312"
  }
]