[
  {
    "pos": {
      "x": -1.986823,
      "y": 4.516841,
      "z": -4.64237
    },
    "rot": {
      "w": -1,
      "x": 0,
      "y": -0.000002948446,
      "z": 0
    },
    "color": -3589831,
    "materialId": 0,
    "type": "1x2SlopeInverted",
    "usingNewColor": true,
    "user": "962b353ab27bc2d1f173ebddb54bbc97"
  },
  {
    "pos": {
      "x": -0.08030938,
      "y": 1.361456,
      "z": -0.6894365
    },
    "rot": {
      "w": 4.371139e-8,
      "x": 0,
      "y": -1,
      "z": 0
    },
    "color": -3589831,
    "materialId": 0,
    "type": "4x4CornerSlope",
    "usingNewColor": true,
    "user": "962b353ab27bc2d1f173ebddb54bbc97"
  },
  {
    "pos": {
      "x": 0.8167702,
      "y": 0.757232,
      "z": 2.502936
    },
    "rot": {
      "w": -1,
      "x": 0,
      "y": -8.742278e-8,
      "z": 0
    },
    "color": -15724784,
    "materialId": 0,
    "type": "2x2Corner",
    "usingNewColor": true,
    "user": "962b353ab27bc2d1f173ebddb54bbc97"
  },
  {
    "pos": {
      "x": 0.1159537,
      "y": 1.63,
      "z": -0.7455125
    },
    "rot": {
      "w": -0.7071066,
      "x": 0,
      "y": -0.7071071,
      "z": 0
    },
    "color": -3589831,
    "materialId": 0,
    "type": "1x2SlopeInverted",
    "usingNewColor": true,
    "user": "962b353ab27bc2d1f173ebddb54bbc97"
  },
  {
    "pos": {
      "x": -2.51954,
      "y": 4.785385,
      "z": -5.034892
    },
    "rot": {
      "w": 0.000002992157,
      "x": 0,
      "y": -1,
      "z": 0
    },
    "color": -9512475,
    "materialId": 0,
    "type": "3x3CornerSlope",
    "usingNewColor": true,
    "user": "962b353ab27bc2d1f173ebddb54bbc97"
  },
  {
    "pos": {
      "x": -2.267185,
      "y": 3.174125,
      "z": -2.483659
    },
    "rot": {
      "w": 0.000001442436,
      "x": 0,
      "y": -1,
      "z": 0
    },
    "color": -12991188,
    "materialId": 0,
    "type": "2x2CornerSlope",
    "usingNewColor": true,
    "user": "962b353ab27bc2d1f173ebddb54bbc97"
  },
  {
    "pos": {
      "x": -2.323195,
      "y": 2.972718,
      "z": -2.14727
    },
    "rot": {
      "w": -0.707106,
      "x": 0,
      "y": -0.7071076,
      "z": 0
    },
    "color": -2433228,
    "materialId": 0,
    "type": "2x2CornerSlope",
    "usingNewColor": true,
    "user": "962b353ab27bc2d1f173ebddb54bbc97"
  },
  {
    "pos": {
      "x": -3.108446,
      "y": 6.530915,
      "z": -4.333951
    },
    "rot": {
      "w": 0.000003679595,
      "x": 0,
      "y": -1,
      "z": 0
    },
    "color": -9535771,
    "materialId": 0,
    "type": "4x4CornerSlope",
    "usingNewColor": true,
    "user": "962b353ab27bc2d1f173ebddb54bbc97"
  },
  {
    "pos": {
      "x": -0.248536,
      "y": 1.428592,
      "z": -0.7735492
    },
    "rot": {
      "w": -1,
      "x": 0,
      "y": -8.742278e-8,
      "z": 0
    },
    "color": -3589831,
    "materialId": 0,
    "type": "1x4Slope",
    "usingNewColor": true,
    "user": "962b353ab27bc2d1f173ebddb54bbc97"
  },
  {
    "pos": {
      "x": -2.211108,
      "y": 3.039854,
      "z": -2.25942
    },
    "rot": {
      "w": -0.7071059,
      "x": 0,
      "y": -0.7071078,
      "z": 0
    },
    "color": -12991188,
    "materialId": 0,
    "type": "4x4CornerSlope",
    "usingNewColor": true,
    "user": "962b353ab27bc2d1f173ebddb54bbc97"
  },
  {
    "pos": {
      "x": 0.3681672,
      "y": 1.025776,
      "z": -0.5772851
    },
    "rot": {
      "w": 0.7071069,
      "x": 0,
      "y": -0.7071067,
      "z": 0
    },
    "color": -3589831,
    "materialId": 0,
    "type": "4x4CornerSlope",
    "usingNewColor": true,
    "user": "962b353ab27bc2d1f173ebddb54bbc97"
  },
  {
    "pos": {
      "x": -4.033696,
      "y": 5.859558,
      "z": -4.978809
    },
    "rot": {
      "w": 0.7071091,
      "x": 0,
      "y": -0.7071044,
      "z": 0
    },
    "color": -9512475,
    "materialId": 0,
    "type": "1x3Slope",
    "usingNewColor": true,
    "user": "962b353ab27bc2d1f173ebddb54bbc97"
  },
  {
    "pos": {
      "x": -2.407245,
      "y": 2.905582,
      "z": -2.063157
    },
    "rot": {
      "w": -0.7071061,
      "x": 0,
      "y": -0.7071075,
      "z": 0
    },
    "color": -2433228,
    "materialId": 0,
    "type": "3x3CornerSlope",
    "usingNewColor": true,
    "user": "962b353ab27bc2d1f173ebddb54bbc97"
  },
  {
    "pos": {
      "x": -2.239149,
      "y": 3.57694,
      "z": -2.84796
    },
    "rot": {
      "w": -0.7071056,
      "x": 0,
      "y": -0.707108,
      "z": 0
    },
    "color": -12991188,
    "materialId": 0,
    "type": "1x3Slope",
    "usingNewColor": true,
    "user": "962b353ab27bc2d1f173ebddb54bbc97"
  },
  {
    "pos": {
      "x": -0.0803118,
      "y": 1.831409,
      "z": -0.969815
    },
    "rot": {
      "w": 6.079713e-7,
      "x": 0,
      "y": -1,
      "z": 0
    },
    "color": -5820200,
    "materialId": 0,
    "type": "4x4CornerSlope",
    "usingNewColor": true,
    "user": "962b353ab27bc2d1f173ebddb54bbc97"
  },
  {
    "pos": {
      "x": 0.05987633,
      "y": 1.764272,
      "z": -0.8296273
    },
    "rot": {
      "w": 5.205485e-7,
      "x": 0,
      "y": -1,
      "z": 0
    },
    "color": -3589831,
    "materialId": 0,
    "type": "3x3CornerSlope",
    "usingNewColor": true,
    "user": "962b353ab27bc2d1f173ebddb54bbc97"
  },
  {
    "pos": {
      "x": -2.407243,
      "y": 2.435631,
      "z": -1.390251
    },
    "rot": {
      "w": 6.079713e-7,
      "x": 0,
      "y": -1,
      "z": 0
    },
    "color": -1731730,
    "materialId": 0,
    "type": "3x3CornerSlope",
    "usingNewColor": true,
    "user": "962b353ab27bc2d1f173ebddb54bbc97"
  },
  {
    "pos": {
      "x": -1.70644,
      "y": 4.046891,
      "z": -3.548904
    },
    "rot": {
      "w": 0.000002396111,
      "x": 0,
      "y": -1,
      "z": 0
    },
    "color": -3589831,
    "materialId": 0,
    "type": "4x4CornerSlope",
    "usingNewColor": true,
    "user": "962b353ab27bc2d1f173ebddb54bbc97"
  },
  {
    "pos": {
      "x": -3.500977,
      "y": 6.329508,
      "z": -4.165723
    },
    "rot": {
      "w": -1,
      "x": 0,
      "y": -0.000003435224,
      "z": 0
    },
    "color": -9512475,
    "materialId": 0,
    "type": "4x4CornerSlope",
    "usingNewColor": true,
    "user": "962b353ab27bc2d1f173ebddb54bbc97"
  },
  {
    "pos": {
      "x": -3.36079,
      "y": 6.799458,
      "z": -5.006853
    },
    "rot": {
      "w": -0.707104,
      "x": 0,
      "y": -0.7071096,
      "z": 0
    },
    "color": -5820200,
    "materialId": 0,
    "type": "1x4Slope",
    "usingNewColor": true,
    "user": "962b353ab27bc2d1f173ebddb54bbc97"
  },
  {
    "pos": {
      "x": -1.790556,
      "y": 4.315434,
      "z": -4.221807
    },
    "rot": {
      "w": -0.7071047,
      "x": 0,
      "y": -0.7071088,
      "z": 0
    },
    "color": -3589831,
    "materialId": 0,
    "type": "1x4Slope",
    "usingNewColor": true,
    "user": "962b353ab27bc2d1f173ebddb54bbc97"
  },
  {
    "pos": {
      "x": -4.033698,
      "y": 5.725286,
      "z": -5.287222
    },
    "rot": {
      "w": 0.707109,
      "x": 0,
      "y": -0.7071046,
      "z": 0
    },
    "color": -9512475,
    "materialId": 0,
    "type": "1x4Slope",
    "usingNewColor": true,
    "user": "962b353ab27bc2d1f173ebddb54bbc97"
  },
  {
    "pos": {
      "x": -2.155041,
      "y": 3.778347,
      "z": -3.268528
    },
    "rot": {
      "w": -0.7071054,
      "x": 0,
      "y": -0.7071083,
      "z": 0
    },
    "color": -2581240,
    "materialId": 0,
    "type": "4x4CornerSlope",
    "usingNewColor": true,
    "user": "962b353ab27bc2d1f173ebddb54bbc97"
  },
  {
    "pos": {
      "x": -2.323261,
      "y": 3.509804,
      "z": -2.707772
    },
    "rot": {
      "w": -0.7071058,
      "x": 0,
      "y": -0.7071079,
      "z": 0
    },
    "color": -12991188,
    "materialId": 0,
    "type": "4x4CornerSlope",
    "usingNewColor": true,
    "user": "962b353ab27bc2d1f173ebddb54bbc97"
  },
  {
    "pos": {
      "x": -3.360787,
      "y": 6.665186,
      "z": -4.670401
    },
    "rot": {
      "w": -0.7071042,
      "x": 0,
      "y": -0.7071095,
      "z": 0
    },
    "color": -5820200,
    "materialId": 0,
    "type": "1x4Slope",
    "usingNewColor": true,
    "user": "962b353ab27bc2d1f173ebddb54bbc97"
  },
  {
    "pos": {
      "x": -2.098974,
      "y": 4.583977,
      "z": -4.726482
    },
    "rot": {
      "w": -0.000002992157,
      "x": 0,
      "y": 1,
      "z": 0
    },
    "color": -3589831,
    "materialId": 0,
    "type": "4x4CornerSlope",
    "usingNewColor": true,
    "user": "962b353ab27bc2d1f173ebddb54bbc97"
  },
  {
    "pos": {
      "x": -2.014853,
      "y": 3.845483,
      "z": -3.408717
    },
    "rot": {
      "w": -0.7071053,
      "x": 0,
      "y": -0.7071083,
      "z": 0
    },
    "color": -2581240,
    "materialId": 0,
    "type": "3x3CornerSlope",
    "usingNewColor": true,
    "user": "962b353ab27bc2d1f173ebddb54bbc97"
  },
  {
    "pos": {
      "x": -0.3606881,
      "y": 1.965681,
      "z": -1.081965
    },
    "rot": {
      "w": 0.7071072,
      "x": 0,
      "y": -0.7071064,
      "z": 0
    },
    "color": -5820200,
    "materialId": 0,
    "type": "4x4CornerSlope",
    "usingNewColor": true,
    "user": "962b353ab27bc2d1f173ebddb54bbc97"
  },
  {
    "pos": {
      "x": -2.183072,
      "y": 3.106989,
      "z": -2.399609
    },
    "rot": {
      "w": 0.000001355013,
      "x": 0,
      "y": -1,
      "z": 0
    },
    "color": -12991188,
    "materialId": 0,
    "type": "3x3CornerSlope",
    "usingNewColor": true,
    "user": "962b353ab27bc2d1f173ebddb54bbc97"
  },
  {
    "pos": {
      "x": 0.08779082,
      "y": 1.227184,
      "z": -0.52121
    },
    "rot": {
      "w": 1.311342e-7,
      "x": 0,
      "y": -1,
      "z": 0
    },
    "color": -3589831,
    "materialId": 0,
    "type": "4x4CornerSlope",
    "usingNewColor": true,
    "user": "962b353ab27bc2d1f173ebddb54bbc97"
  },
  {
    "pos": {
      "x": -2.098829,
      "y": 2.30136,
      "z": -1.081838
    },
    "rot": {
      "w": 6.079713e-7,
      "x": 0,
      "y": -1,
      "z": 0
    },
    "color": -1731730,
    "materialId": 0,
    "type": "4x4CornerSlope",
    "usingNewColor": true,
    "user": "962b353ab27bc2d1f173ebddb54bbc97"
  },
  {
    "pos": {
      "x": -3.613128,
      "y": 6.262372,
      "z": -4.333948
    },
    "rot": {
      "w": -1,
      "x": 0,
      "y": -0.000003347801,
      "z": 0
    },
    "color": -9512475,
    "materialId": 0,
    "type": "4x4CornerSlope",
    "usingNewColor": true,
    "user": "962b353ab27bc2d1f173ebddb54bbc97"
  },
  {
    "pos": {
      "x": -2.547705,
      "y": 5.053928,
      "z": -5.371344
    },
    "rot": {
      "w": 0.000003111367,
      "x": 0,
      "y": -1,
      "z": 0
    },
    "color": -9512475,
    "materialId": 0,
    "type": "1x4Slope",
    "usingNewColor": true,
    "user": "962b353ab27bc2d1f173ebddb54bbc97"
  },
  {
    "pos": {
      "x": -2.379478,
      "y": 4.986792,
      "z": -5.287232
    },
    "rot": {
      "w": 0.000003083548,
      "x": 0,
      "y": -1,
      "z": 0
    },
    "color": -9512475,
    "materialId": 0,
    "type": "4x4CornerSlope",
    "usingNewColor": true,
    "user": "962b353ab27bc2d1f173ebddb54bbc97"
  },
  {
    "pos": {
      "x": -3.220594,
      "y": 6.396644,
      "z": -4.081612
    },
    "rot": {
      "w": -0.000003478935,
      "x": 0,
      "y": 1,
      "z": 0
    },
    "color": -9535771,
    "materialId": 0,
    "type": "1x8",
    "usingNewColor": true,
    "user": "962b353ab27bc2d1f173ebddb54bbc97"
  },
  {
    "pos": {
      "x": -1.874672,
      "y": 4.449706,
      "z": -4.558258
    },
    "rot": {
      "w": 0.000002994141,
      "x": 0,
      "y": -1,
      "z": 0
    },
    "color": -3589831,
    "materialId": 0,
    "type": "4x4CornerSlope",
    "usingNewColor": true,
    "user": "962b353ab27bc2d1f173ebddb54bbc97"
  },
  {
    "pos": {
      "x": -0.8094092,
      "y": 0.757232,
      "z": -1.138038
    },
    "rot": {
      "w": -0.7071069,
      "x": 0,
      "y": 0.7071068,
      "z": 0
    },
    "color": -15130770,
    "materialId": 0,
    "type": "4x4CornerSlope",
    "usingNewColor": true,
    "user": "962b353ab27bc2d1f173ebddb54bbc97"
  },
  {
    "pos": {
      "x": -2.379336,
      "y": 3.308397,
      "z": -2.539608
    },
    "rot": {
      "w": 0.000001442436,
      "x": 0,
      "y": -1,
      "z": 0
    },
    "color": -12991188,
    "materialId": 0,
    "type": "2x2CornerSlope",
    "usingNewColor": true,
    "user": "962b353ab27bc2d1f173ebddb54bbc97"
  },
  {
    "pos": {
      "x": -2.435348,
      "y": 3.375533,
      "z": -2.595621
    },
    "rot": {
      "w": -0.7071058,
      "x": 0,
      "y": -0.7071078,
      "z": 0
    },
    "color": -12991188,
    "materialId": 0,
    "type": "2x2CornerSlope",
    "usingNewColor": true,
    "user": "962b353ab27bc2d1f173ebddb54bbc97"
  },
  {
    "pos": {
      "x": -3.94958,
      "y": 6.128101,
      "z": -4.418058
    },
    "rot": {
      "w": 1,
      "x": 0,
      "y": 0.000003172955,
      "z": 0
    },
    "color": -9512475,
    "materialId": 0,
    "type": "1x4Slope",
    "usingNewColor": true,
    "user": "962b353ab27bc2d1f173ebddb54bbc97"
  },
  {
    "pos": {
      "x": -4.033693,
      "y": 6.060965,
      "z": -4.502171
    },
    "rot": {
      "w": 0.7071091,
      "x": 0,
      "y": -0.7071044,
      "z": 0
    },
    "color": -9512475,
    "materialId": 0,
    "type": "1x4Slope",
    "usingNewColor": true,
    "user": "962b353ab27bc2d1f173ebddb54bbc97"
  },
  {
    "pos": {
      "x": -2.575615,
      "y": 4.85252,
      "z": -5.147042
    },
    "rot": {
      "w": -0.7071047,
      "x": 0,
      "y": -0.7071089,
      "z": 0
    },
    "color": -9512475,
    "materialId": 0,
    "type": "3x3CornerSlope",
    "usingNewColor": true,
    "user": "962b353ab27bc2d1f173ebddb54bbc97"
  },
  {
    "pos": {
      "x": -4.033694,
      "y": 5.993829,
      "z": -4.670396
    },
    "rot": {
      "w": 0.7071091,
      "x": 0,
      "y": -0.7071044,
      "z": 0
    },
    "color": -9512475,
    "materialId": 0,
    "type": "1x4Slope",
    "usingNewColor": true,
    "user": "962b353ab27bc2d1f173ebddb54bbc97"
  },
  {
    "pos": {
      "x": -2.547433,
      "y": 2.838446,
      "z": -2.091194
    },
    "rot": {
      "w": -1,
      "x": 0,
      "y": -9.675833e-7,
      "z": 0
    },
    "color": -15724784,
    "materialId": 0,
    "type": "4x4CornerSlope",
    "usingNewColor": true,
    "user": "962b353ab27bc2d1f173ebddb54bbc97"
  },
  {
    "pos": {
      "x": -2.379351,
      "y": 4.718249,
      "z": -4.95078
    },
    "rot": {
      "w": 0.000002992157,
      "x": 0,
      "y": -1,
      "z": 0
    },
    "color": -9512475,
    "materialId": 0,
    "type": "4x4CornerSlope",
    "usingNewColor": true,
    "user": "962b353ab27bc2d1f173ebddb54bbc97"
  },
  {
    "pos": {
      "x": -2.827809,
      "y": 2.637039,
      "z": -1.810817
    },
    "rot": {
      "w": -0.7071064,
      "x": 0,
      "y": -0.7071072,
      "z": 0
    },
    "color": -15724784,
    "materialId": 0,
    "type": "4x4CornerSlope",
    "usingNewColor": true,
    "user": "962b353ab27bc2d1f173ebddb54bbc97"
  },
  {
    "pos": {
      "x": -4.033697,
      "y": 5.792422,
      "z": -5.118997
    },
    "rot": {
      "w": 0.7071091,
      "x": 0,
      "y": -0.7071044,
      "z": 0
    },
    "color": -9512475,
    "materialId": 0,
    "type": "1x4Slope",
    "usingNewColor": true,
    "user": "962b353ab27bc2d1f173ebddb54bbc97"
  },
  {
    "pos": {
      "x": -2.687621,
      "y": 2.77131,
      "z": -2.119231
    },
    "rot": {
      "w": -0.7071061,
      "x": 0,
      "y": -0.7071075,
      "z": 0
    },
    "color": -15724784,
    "materialId": 0,
    "type": "3x3CornerSlope",
    "usingNewColor": true,
    "user": "962b353ab27bc2d1f173ebddb54bbc97"
  },
  {
    "pos": {
      "x": -1.762516,
      "y": 3.979755,
      "z": -3.633018
    },
    "rot": {
      "w": 0.00000233849,
      "x": 0,
      "y": -1,
      "z": 0
    },
    "color": -3589831,
    "materialId": 0,
    "type": "1x2SlopeInverted",
    "usingNewColor": true,
    "user": "962b353ab27bc2d1f173ebddb54bbc97"
  },
  {
    "pos": {
      "x": 0.1999417,
      "y": 1.092912,
      "z": -0.4931723
    },
    "rot": {
      "w": 1,
      "x": 0,
      "y": 4.371139e-8,
      "z": 0
    },
    "color": -3589831,
    "materialId": 0,
    "type": "1x4Slope",
    "usingNewColor": true,
    "user": "962b353ab27bc2d1f173ebddb54bbc97"
  },
  {
    "pos": {
      "x": -2.323261,
      "y": 3.241261,
      "z": -2.539608
    },
    "rot": {
      "w": 0.000001442436,
      "x": 0,
      "y": -1,
      "z": 0
    },
    "color": -12991188,
    "materialId": 0,
    "type": "2x2CornerSlope",
    "usingNewColor": true,
    "user": "962b353ab27bc2d1f173ebddb54bbc97"
  },
  {
    "pos": {
      "x": -2.659583,
      "y": 2.569903,
      "z": -1.642591
    },
    "rot": {
      "w": 6.079713e-7,
      "x": 0,
      "y": -1,
      "z": 0
    },
    "color": -1731730,
    "materialId": 0,
    "type": "4x4CornerSlope",
    "usingNewColor": true,
    "user": "962b353ab27bc2d1f173ebddb54bbc97"
  },
  {
    "pos": {
      "x": -2.435411,
      "y": 3.442668,
      "z": -2.651633
    },
    "rot": {
      "w": -1,
      "x": 0,
      "y": -0.00000144442,
      "z": 0
    },
    "color": -12991188,
    "materialId": 0,
    "type": "2x2CornerSlope",
    "usingNewColor": true,
    "user": "962b353ab27bc2d1f173ebddb54bbc97"
  },
  {
    "pos": {
      "x": -3.781354,
      "y": 6.195237,
      "z": -4.418059
    },
    "rot": {
      "w": -1,
      "x": 0,
      "y": -0.000003260378,
      "z": 0
    },
    "color": -9512475,
    "materialId": 0,
    "type": "1x4Slope",
    "usingNewColor": true,
    "user": "962b353ab27bc2d1f173ebddb54bbc97"
  },
  {
    "pos": {
      "x": -0.2205001,
      "y": 1.898545,
      "z": -1.110003
    },
    "rot": {
      "w": 6.079713e-7,
      "x": 0,
      "y": -1,
      "z": 0
    },
    "color": -5820200,
    "materialId": 0,
    "type": "3x3CornerSlope",
    "usingNewColor": true,
    "user": "962b353ab27bc2d1f173ebddb54bbc97"
  },
  {
    "pos": {
      "x": -1.790554,
      "y": 4.114027,
      "z": -3.71713
    },
    "rot": {
      "w": -0.7071052,
      "x": 0,
      "y": -0.7071085,
      "z": 0
    },
    "color": -3589831,
    "materialId": 0,
    "type": "1x4Slope",
    "usingNewColor": true,
    "user": "962b353ab27bc2d1f173ebddb54bbc97"
  },
  {
    "pos": {
      "x": -2.996307,
      "y": 5.255335,
      "z": -5.371341
    },
    "rot": {
      "w": 0.000003111367,
      "x": 0,
      "y": -1,
      "z": 0
    },
    "color": -9512475,
    "materialId": 0,
    "type": "1x4Slope",
    "usingNewColor": true,
    "user": "962b353ab27bc2d1f173ebddb54bbc97"
  },
  {
    "pos": {
      "x": -3.304721,
      "y": 5.389607,
      "z": -5.371339
    },
    "rot": {
      "w": 0.000003111367,
      "x": 0,
      "y": -1,
      "z": 0
    },
    "color": -9512475,
    "materialId": 0,
    "type": "1x3Slope",
    "usingNewColor": true,
    "user": "962b353ab27bc2d1f173ebddb54bbc97"
  },
  {
    "pos": {
      "x": 0.6765816,
      "y": 0.8915039,
      "z": -0.8856995
    },
    "rot": {
      "w": 0.7071069,
      "x": 0,
      "y": -0.7071067,
      "z": 0
    },
    "color": -1731730,
    "materialId": 0,
    "type": "3x3CornerSlope",
    "usingNewColor": true,
    "user": "962b353ab27bc2d1f173ebddb54bbc97"
  },
  {
    "pos": {
      "x": 0.8167075,
      "y": 0.757232,
      "z": 4.185127
    },
    "rot": {
      "w": -0.7071069,
      "x": 0,
      "y": 0.7071068,
      "z": 0
    },
    "color": -15724784,
    "materialId": 0,
    "type": "2x2Corner",
    "usingNewColor": true,
    "user": "962b353ab27bc2d1f173ebddb54bbc97"
  },
  {
    "pos": {
      "x": -0.8654213,
      "y": 0.757232,
      "z": 2.502873
    },
    "rot": {
      "w": -0.7071068,
      "x": 0,
      "y": -0.7071069,
      "z": 0
    },
    "color": -15724784,
    "materialId": 0,
    "type": "2x2Corner",
    "usingNewColor": true,
    "user": "962b353ab27bc2d1f173ebddb54bbc97"
  },
  {
    "pos": {
      "x": -0.8094087,
      "y": 0.757232,
      "z": -2.708142
    },
    "rot": {
      "w": -4.371139e-8,
      "x": 0,
      "y": 1,
      "z": 0
    },
    "color": -14258663,
    "materialId": 0,
    "type": "4x4CornerSlope",
    "usingNewColor": true,
    "user": "962b353ab27bc2d1f173ebddb54bbc97"
  },
  {
    "pos": {
      "x": -3.52902,
      "y": 6.93373,
      "z": -5.343306
    },
    "rot": {
      "w": -0.707104,
      "x": 0,
      "y": -0.7071096,
      "z": 0
    },
    "color": -5820200,
    "materialId": 0,
    "type": "1x4Slope",
    "usingNewColor": true,
    "user": "962b353ab27bc2d1f173ebddb54bbc97"
  },
  {
    "pos": {
      "x": -3.78136,
      "y": 5.591014,
      "z": -5.371336
    },
    "rot": {
      "w": 0.000003111367,
      "x": 0,
      "y": -1,
      "z": 0
    },
    "color": -9512475,
    "materialId": 0,
    "type": "1x4Slope",
    "usingNewColor": true,
    "user": "962b353ab27bc2d1f173ebddb54bbc97"
  },
  {
    "pos": {
      "x": -2.267054,
      "y": 2.368495,
      "z": -1.250063
    },
    "rot": {
      "w": 6.079713e-7,
      "x": 0,
      "y": -1,
      "z": 0
    },
    "color": -1731730,
    "materialId": 0,
    "type": "4x4CornerSlope",
    "usingNewColor": true,
    "user": "962b353ab27bc2d1f173ebddb54bbc97"
  },
  {
    "pos": {
      "x": 0.2279787,
      "y": 1.160048,
      "z": -0.4931723
    },
    "rot": {
      "w": -8.742278e-8,
      "x": 0,
      "y": 1,
      "z": 0
    },
    "color": -3589831,
    "materialId": 0,
    "type": "1x3Slope",
    "usingNewColor": true,
    "user": "962b353ab27bc2d1f173ebddb54bbc97"
  },
  {
    "pos": {
      "x": -0.08030944,
      "y": 1.495728,
      "z": -0.8576629
    },
    "rot": {
      "w": -1,
      "x": 0,
      "y": -1.748456e-7,
      "z": 0
    },
    "color": -3589831,
    "materialId": 0,
    "type": "4x4CornerSlope",
    "usingNewColor": true,
    "user": "962b353ab27bc2d1f173ebddb54bbc97"
  },
  {
    "pos": {
      "x": -1.874666,
      "y": 3.912619,
      "z": -3.548905
    },
    "rot": {
      "w": -0.7071052,
      "x": 0,
      "y": -0.7071084,
      "z": 0
    },
    "color": -3589831,
    "materialId": 0,
    "type": "4x4CornerSlope",
    "usingNewColor": true,
    "user": "962b353ab27bc2d1f173ebddb54bbc97"
  },
  {
    "pos": {
      "x": 0.536393,
      "y": 0.9586399,
      "z": -0.7455109
    },
    "rot": {
      "w": 0.7071069,
      "x": 0,
      "y": -0.7071067,
      "z": 0
    },
    "color": -3589831,
    "materialId": 0,
    "type": "4x4CornerSlope",
    "usingNewColor": true,
    "user": "962b353ab27bc2d1f173ebddb54bbc97"
  },
  {
    "pos": {
      "x": -1.930703,
      "y": 2.234224,
      "z": -1.025826
    },
    "rot": {
      "w": 6.079713e-7,
      "x": 0,
      "y": -1,
      "z": 0
    },
    "color": -15724784,
    "materialId": 0,
    "type": "4x2",
    "usingNewColor": true,
    "user": "962b353ab27bc2d1f173ebddb54bbc97"
  },
  {
    "pos": {
      "x": -3.444906,
      "y": 6.866594,
      "z": -5.175079
    },
    "rot": {
      "w": 0.000003918014,
      "x": 0,
      "y": -1,
      "z": 0
    },
    "color": -5820200,
    "materialId": 0,
    "type": "4x4CornerSlope",
    "usingNewColor": true,
    "user": "962b353ab27bc2d1f173ebddb54bbc97"
  },
  {
    "pos": {
      "x": -2.491565,
      "y": 4.919656,
      "z": -5.231156
    },
    "rot": {
      "w": -0.7071046,
      "x": 0,
      "y": -0.707109,
      "z": 0
    },
    "color": -9512475,
    "materialId": 0,
    "type": "2x2CornerSlope",
    "usingNewColor": true,
    "user": "962b353ab27bc2d1f173ebddb54bbc97"
  },
  {
    "pos": {
      "x": 0.1159537,
      "y": 1.697136,
      "z": -0.7455128
    },
    "rot": {
      "w": -0.7071071,
      "x": 0,
      "y": 0.7071065,
      "z": 0
    },
    "color": -3589831,
    "materialId": 0,
    "type": "1x2SlopeInverted",
    "usingNewColor": true,
    "user": "962b353ab27bc2d1f173ebddb54bbc97"
  },
  {
    "pos": {
      "x": -3.164533,
      "y": 5.322471,
      "z": -5.37134
    },
    "rot": {
      "w": 0.000003111367,
      "x": 0,
      "y": -1,
      "z": 0
    },
    "color": -9512475,
    "materialId": 0,
    "type": "1x4Slope",
    "usingNewColor": true,
    "user": "962b353ab27bc2d1f173ebddb54bbc97"
  },
  {
    "pos": {
      "x": -3.024332,
      "y": 6.463779,
      "z": -4.165727
    },
    "rot": {
      "w": -0.7071043,
      "x": 0,
      "y": -0.7071094,
      "z": 0
    },
    "color": -9535771,
    "materialId": 0,
    "type": "1x4Slope",
    "usingNewColor": true,
    "user": "962b353ab27bc2d1f173ebddb54bbc97"
  },
  {
    "pos": {
      "x": -2.239162,
      "y": 4.651113,
      "z": -4.810594
    },
    "rot": {
      "w": 0.000002992157,
      "x": 0,
      "y": -1,
      "z": 0
    },
    "color": -3589831,
    "materialId": 0,
    "type": "3x3CornerSlope",
    "usingNewColor": true,
    "user": "962b353ab27bc2d1f173ebddb54bbc97"
  },
  {
    "pos": {
      "x": -2.687893,
      "y": 5.121064,
      "z": -5.371343
    },
    "rot": {
      "w": 0.000003111367,
      "x": 0,
      "y": -1,
      "z": 0
    },
    "color": -9512475,
    "materialId": 0,
    "type": "1x3Slope",
    "usingNewColor": true,
    "user": "962b353ab27bc2d1f173ebddb54bbc97"
  },
  {
    "pos": {
      "x": -1.790555,
      "y": 4.248298,
      "z": -4.053581
    },
    "rot": {
      "w": -0.7071049,
      "x": 0,
      "y": -0.7071087,
      "z": 0
    },
    "color": -3589831,
    "materialId": 0,
    "type": "1x4Slope",
    "usingNewColor": true,
    "user": "962b353ab27bc2d1f173ebddb54bbc97"
  },
  {
    "pos": {
      "x": -3.360788,
      "y": 6.732322,
      "z": -4.838627
    },
    "rot": {
      "w": -0.7071041,
      "x": 0,
      "y": -0.7071095,
      "z": 0
    },
    "color": -5820200,
    "materialId": 0,
    "type": "1x4Slope",
    "usingNewColor": true,
    "user": "962b353ab27bc2d1f173ebddb54bbc97"
  },
  {
    "pos": {
      "x": -2.127003,
      "y": 3.711212,
      "z": -3.128341
    },
    "rot": {
      "w": 0.00000195106,
      "x": 0,
      "y": -1,
      "z": 0
    },
    "color": -2581240,
    "materialId": 0,
    "type": "3x3CornerSlope",
    "usingNewColor": true,
    "user": "962b353ab27bc2d1f173ebddb54bbc97"
  },
  {
    "pos": {
      "x": -0.697148,
      "y": 2.032816,
      "z": -0.9978521
    },
    "rot": {
      "w": 5.205485e-7,
      "x": 0,
      "y": -1,
      "z": 0
    },
    "color": -5820200,
    "materialId": 0,
    "type": "1x10",
    "usingNewColor": true,
    "user": "962b353ab27bc2d1f173ebddb54bbc97"
  },
  {
    "pos": {
      "x": -0.02429679,
      "y": 1.29432,
      "z": -0.6333604
    },
    "rot": {
      "w": 0.7071069,
      "x": 0,
      "y": -0.7071067,
      "z": 0
    },
    "color": -3589831,
    "materialId": 0,
    "type": "2x2Slope",
    "usingNewColor": true,
    "user": "962b353ab27bc2d1f173ebddb54bbc97"
  },
  {
    "pos": {
      "x": -1.650428,
      "y": 2.167088,
      "z": -0.9978511
    },
    "rot": {
      "w": 6.079713e-7,
      "x": 0,
      "y": -1,
      "z": 0
    },
    "color": -15990000,
    "materialId": 0,
    "type": "1x8",
    "usingNewColor": true,
    "user": "962b353ab27bc2d1f173ebddb54bbc97"
  },
  {
    "pos": {
      "x": -3.444909,
      "y": 5.456743,
      "z": -5.371338
    },
    "rot": {
      "w": 0.000003111367,
      "x": 0,
      "y": -1,
      "z": 0
    },
    "color": -9512475,
    "materialId": 0,
    "type": "1x4Slope",
    "usingNewColor": true,
    "user": "962b353ab27bc2d1f173ebddb54bbc97"
  },
  {
    "pos": {
      "x": -0.865483,
      "y": 0.757232,
      "z": 4.185066
    },
    "rot": {
      "w": -4.371139e-8,
      "x": 0,
      "y": 1,
      "z": 0
    },
    "color": -15724784,
    "materialId": 0,
    "type": "2x2Corner",
    "usingNewColor": true,
    "user": "962b353ab27bc2d1f173ebddb54bbc97"
  },
  {
    "pos": {
      "x": -2.828081,
      "y": 5.1882,
      "z": -5.371342
    },
    "rot": {
      "w": 0.000003111367,
      "x": 0,
      "y": -1,
      "z": 0
    },
    "color": -9512475,
    "materialId": 0,
    "type": "1x4Slope",
    "usingNewColor": true,
    "user": "962b353ab27bc2d1f173ebddb54bbc97"
  },
  {
    "pos": {
      "x": -1.790557,
      "y": 4.38257,
      "z": -4.390032
    },
    "rot": {
      "w": -0.7071046,
      "x": 0,
      "y": -0.7071089,
      "z": 0
    },
    "color": -3589831,
    "materialId": 0,
    "type": "1x4Slope",
    "usingNewColor": true,
    "user": "962b353ab27bc2d1f173ebddb54bbc97"
  },
  {
    "pos": {
      "x": -3.276673,
      "y": 6.598051,
      "z": -4.502175
    },
    "rot": {
      "w": 0.000003707413,
      "x": 0,
      "y": -1,
      "z": 0
    },
    "color": -5820200,
    "materialId": 0,
    "type": "4x4CornerSlope",
    "usingNewColor": true,
    "user": "962b353ab27bc2d1f173ebddb54bbc97"
  },
  {
    "pos": {
      "x": 0.7606946,
      "y": 0.757232,
      "z": -1.138038
    },
    "rot": {
      "w": -1,
      "x": 0,
      "y": -8.742278e-8,
      "z": 0
    },
    "color": -9535771,
    "materialId": 0,
    "type": "4x4CornerSlope",
    "usingNewColor": true,
    "user": "962b353ab27bc2d1f173ebddb54bbc97"
  },
  {
    "pos": {
      "x": -1.201826,
      "y": 2.099952,
      "z": -0.9978516
    },
    "rot": {
      "w": 6.079713e-7,
      "x": 0,
      "y": -1,
      "z": 0
    },
    "color": -15990000,
    "materialId": 0,
    "type": "1x10",
    "usingNewColor": true,
    "user": "962b353ab27bc2d1f173ebddb54bbc97"
  },
  {
    "pos": {
      "x": 0.7606952,
      "y": 0.757232,
      "z": -2.708142
    },
    "rot": {
      "w": -0.7071068,
      "x": 0,
      "y": -0.7071069,
      "z": 0
    },
    "color": -9512475,
    "materialId": 0,
    "type": "4x4CornerSlope",
    "usingNewColor": true,
    "user": "962b353ab27bc2d1f173ebddb54bbc97"
  },
  {
    "pos": {
      "x": -2.743697,
      "y": 2.704175,
      "z": -1.979043
    },
    "rot": {
      "w": -0.7071062,
      "x": 0,
      "y": -0.7071074,
      "z": 0
    },
    "color": -15724784,
    "materialId": 0,
    "type": "1x4Slope",
    "usingNewColor": true,
    "user": "962b353ab27bc2d1f173ebddb54bbc97"
  },
  {
    "pos": {
      "x": -3.613134,
      "y": 5.523879,
      "z": -5.371337
    },
    "rot": {
      "w": 0.000003111367,
      "x": 0,
      "y": -1,
      "z": 0
    },
    "color": -9512475,
    "materialId": 0,
    "type": "1x4Slope",
    "usingNewColor": true,
    "user": "962b353ab27bc2d1f173ebddb54bbc97"
  },
  {
    "pos": {
      "x": -2.519394,
      "y": 2.502767,
      "z": -1.502402
    },
    "rot": {
      "w": 6.079713e-7,
      "x": 0,
      "y": -1,
      "z": 0
    },
    "color": -1731730,
    "materialId": 0,
    "type": "3x3CornerSlope",
    "usingNewColor": true,
    "user": "962b353ab27bc2d1f173ebddb54bbc97"
  },
  {
    "pos": {
      "x": -3.949585,
      "y": 5.65815,
      "z": -5.371335
    },
    "rot": {
      "w": 0.000003111367,
      "x": 0,
      "y": -1,
      "z": 0
    },
    "color": -9512475,
    "materialId": 0,
    "type": "1x4Slope",
    "usingNewColor": true,
    "user": "962b353ab27bc2d1f173ebddb54bbc97"
  },
  {
    "pos": {
      "x": -4.033695,
      "y": 5.926693,
      "z": -4.838621
    },
    "rot": {
      "w": 0.7071091,
      "x": 0,
      "y": -0.7071044,
      "z": 0
    },
    "color": -9512475,
    "materialId": 0,
    "type": "1x4Slope",
    "usingNewColor": true,
    "user": "962b353ab27bc2d1f173ebddb54bbc97"
  },
  {
    "pos": {
      "x": -2.155036,
      "y": 3.644076,
      "z": -2.988149
    },
    "rot": {
      "w": -0.7071055,
      "x": 0,
      "y": -0.7071082,
      "z": 0
    },
    "color": -12991188,
    "materialId": 0,
    "type": "4x4CornerSlope",
    "usingNewColor": true,
    "user": "962b353ab27bc2d1f173ebddb54bbc97"
  },
  {
    "pos": {
      "x": -1.790555,
      "y": 4.181162,
      "z": -3.885356
    },
    "rot": {
      "w": -0.707105,
      "x": 0,
      "y": -0.7071086,
      "z": 0
    },
    "color": -3589831,
    "materialId": 0,
    "type": "1x4Slope",
    "usingNewColor": true,
    "user": "962b353ab27bc2d1f173ebddb54bbc97"
  },
  {
    "pos": {
      "x": 0.7887321,
      "y": 0.8243679,
      "z": -0.99785
    },
    "rot": {
      "w": -0.7071069,
      "x": 0,
      "y": 0.7071067,
      "z": 0
    },
    "color": -1731730,
    "materialId": 0,
    "type": "3x3CornerSlope",
    "usingNewColor": true,
    "user": "962b353ab27bc2d1f173ebddb54bbc97"
  },
  {
    "pos": {
      "x": 0.03184088,
      "y": 1.562864,
      "z": -0.8576629
    },
    "rot": {
      "w": -1,
      "x": 0,
      "y": -2.622683e-7,
      "z": 0
    },
    "color": -3589831,
    "materialId": 0,
    "type": "4x4CornerSlope",
    "usingNewColor": true,
    "user": "962b353ab27bc2d1f173ebddb54bbc97"
  }
]