[
  {
    "pos": {
      "x": 0.2839311,
      "y": 0.8915039,
      "z": -1.838878
    },
    "rot": {
      "w": 0.7071069,
      "x": 0,
      "y": -0.7071067,
      "z": 0
    },
    "color": -16777216,
    "materialId": 0,
    "type": "1x1",
    "usingNewColor": true,
    "user": "d7d0daee75a94084d9a5d3d9aa78ba8e"
  },
  {
    "pos": {
      "x": 0.3401315,
      "y": 0.734996,
      "z": 3.652413
    },
    "rot": {
      "w": -1,
      "x": 0,
      "y": -8.742278e-8,
      "z": 0
    },
    "color": -6094848,
    "materialId": 0,
    "type": "1x1Tile",
    "usingNewColor": true,
    "user": "d7d0daee75a94084d9a5d3d9aa78ba8e"
  },
  {
    "pos": {
      "x": 0.3120939,
      "y": 0.757232,
      "z": -1.642714
    },
    "rot": {
      "w": -4.371139e-8,
      "x": 0,
      "y": 1,
      "z": 0
    },
    "color": -16777216,
    "materialId": 0,
    "type": "4x4CornerSlope",
    "usingNewColor": true,
    "user": "d7d0daee75a94084d9a5d3d9aa78ba8e"
  },
  {
    "pos": {
      "x": 0.2279813,
      "y": 0.734996,
      "z": 3.540263
    },
    "rot": {
      "w": -0.7071069,
      "x": 0,
      "y": 0.7071068,
      "z": 0
    },
    "color": -6094848,
    "materialId": 0,
    "type": "1x1Tile",
    "usingNewColor": true,
    "user": "d7d0daee75a94084d9a5d3d9aa78ba8e"
  },
  {
    "pos": {
      "x": 0.3681691,
      "y": 0.8243679,
      "z": 3.764564
    },
    "rot": {
      "w": 1,
      "x": 0,
      "y": 4.371139e-8,
      "z": 0
    },
    "color": -15592941,
    "materialId": 0,
    "type": "1x2_1FaceSideStud",
    "usingNewColor": true,
    "user": "d7d0daee75a94084d9a5d3d9aa78ba8e"
  },
  {
    "pos": {
      "x": 0.312094,
      "y": 0.757232,
      "z": -2.091315
    },
    "rot": {
      "w": -0.7071069,
      "x": 0,
      "y": 0.7071068,
      "z": 0
    },
    "color": -16777216,
    "materialId": 0,
    "type": "4x4CornerSlope",
    "usingNewColor": true,
    "user": "d7d0daee75a94084d9a5d3d9aa78ba8e"
  },
  {
    "pos": {
      "x": 0.283931,
      "y": 0.8915039,
      "z": -1.894953
    },
    "rot": {
      "w": 0.7071069,
      "x": 0,
      "y": -0.7071067,
      "z": 0
    },
    "color": -16777216,
    "materialId": 0,
    "type": "1x1",
    "usingNewColor": true,
    "user": "d7d0daee75a94084d9a5d3d9aa78ba8e"
  },
  {
    "pos": {
      "x": 0.2839311,
      "y": 0.9364039,
      "z": -1.866915
    },
    "rot": {
      "w": 0.7071069,
      "x": 0,
      "y": -0.7071067,
      "z": 0
    },
    "color": -16777216,
    "materialId": 0,
    "type": "1x4Tile",
    "usingNewColor": true,
    "user": "d7d0daee75a94084d9a5d3d9aa78ba8e"
  },
  {
    "pos": {
      "x": 0.2279812,
      "y": 0.8915039,
      "z": -1.782903
    },
    "rot": {
      "w": -0.7071068,
      "x": 0,
      "y": -0.7071069,
      "z": 0
    },
    "color": -16777216,
    "materialId": 0,
    "type": "1x3Slope",
    "usingNewColor": true,
    "user": "d7d0daee75a94084d9a5d3d9aa78ba8e"
  },
  {
    "pos": {
      "x": 0.5363948,
      "y": 0.757232,
      "z": -1.838977
    },
    "rot": {
      "w": -4.371139e-8,
      "x": 0,
      "y": 1,
      "z": 0
    },
    "color": -16777216,
    "materialId": 0,
    "type": "1x4Slope",
    "usingNewColor": true,
    "user": "d7d0daee75a94084d9a5d3d9aa78ba8e"
  },
  {
    "pos": {
      "x": 0.3962067,
      "y": 0.757232,
      "z": -1.867015
    },
    "rot": {
      "w": -0.7071069,
      "x": 0,
      "y": 0.7071068,
      "z": 0
    },
    "color": -16777216,
    "materialId": 0,
    "type": "1x4",
    "usingNewColor": true,
    "user": "d7d0daee75a94084d9a5d3d9aa78ba8e"
  },
  {
    "pos": {
      "x": 0.3681698,
      "y": 0.8243679,
      "z": 3.315962
    },
    "rot": {
      "w": 4.371139e-8,
      "x": 0,
      "y": -1,
      "z": 0
    },
    "color": -65536,
    "materialId": 0,
    "type": "1x2_1FaceSideStud",
    "usingNewColor": true,
    "user": "d7d0daee75a94084d9a5d3d9aa78ba8e"
  },
  {
    "pos": {
      "x": 0.3962074,
      "y": 0.757232,
      "z": 3.344001
    },
    "rot": {
      "w": -0.7071067,
      "x": 0,
      "y": -0.7071069,
      "z": 0
    },
    "color": -44032,
    "materialId": 0,
    "type": "1x2SlopeInverted",
    "usingNewColor": true,
    "user": "d7d0daee75a94084d9a5d3d9aa78ba8e"
  },
  {
    "pos": {
      "x": 0.3681696,
      "y": 0.9364039,
      "z": 3.736526
    },
    "rot": {
      "w": 0.7071069,
      "x": 0,
      "y": -0.7071067,
      "z": 0
    },
    "color": -15592941,
    "materialId": 0,
    "type": "2x2Tile",
    "usingNewColor": true,
    "user": "d7d0daee75a94084d9a5d3d9aa78ba8e"
  },
  {
    "pos": {
      "x": 0.4242441,
      "y": 0.734996,
      "z": 3.596338
    },
    "rot": {
      "w": -1,
      "x": 0,
      "y": -8.742278e-8,
      "z": 0
    },
    "color": -6094848,
    "materialId": 0,
    "type": "1x2Tile",
    "usingNewColor": true,
    "user": "d7d0daee75a94084d9a5d3d9aa78ba8e"
  },
  {
    "pos": {
      "x": 0.5083563,
      "y": 0.757232,
      "z": -1.951128
    },
    "rot": {
      "w": -4.371139e-8,
      "x": 0,
      "y": 1,
      "z": 0
    },
    "color": -16777216,
    "materialId": 0,
    "type": "1x3Slope",
    "usingNewColor": true,
    "user": "d7d0daee75a94084d9a5d3d9aa78ba8e"
  },
  {
    "pos": {
      "x": 0.2279812,
      "y": 0.8243679,
      "z": -2.007203
    },
    "rot": {
      "w": 0.7071069,
      "x": 0,
      "y": -0.7071067,
      "z": 0
    },
    "color": -16777216,
    "materialId": 0,
    "type": "1x1",
    "usingNewColor": true,
    "user": "d7d0daee75a94084d9a5d3d9aa78ba8e"
  },
  {
    "pos": {
      "x": 0.3681695,
      "y": 0.8914679,
      "z": 3.315964
    },
    "rot": {
      "w": 3.119323e-7,
      "x": 0,
      "y": -1,
      "z": 0
    },
    "color": -44032,
    "materialId": 0,
    "type": "1x2",
    "usingNewColor": true,
    "user": "d7d0daee75a94084d9a5d3d9aa78ba8e"
  },
  {
    "pos": {
      "x": 0.3680438,
      "y": 0.8243679,
      "z": -1.838878
    },
    "rot": {
      "w": 4.371139e-8,
      "x": 0,
      "y": -1,
      "z": 0
    },
    "color": -16777216,
    "materialId": 0,
    "type": "1x4Slope",
    "usingNewColor": true,
    "user": "d7d0daee75a94084d9a5d3d9aa78ba8e"
  },
  {
    "pos": {
      "x": 0.368044,
      "y": 0.8243679,
      "z": -1.782903
    },
    "rot": {
      "w": 4.371139e-8,
      "x": 0,
      "y": -1,
      "z": 0
    },
    "color": -16777216,
    "materialId": 0,
    "type": "1x4Slope",
    "usingNewColor": true,
    "user": "d7d0daee75a94084d9a5d3d9aa78ba8e"
  },
  {
    "pos": {
      "x": 0.2279813,
      "y": 0.8243679,
      "z": -1.867015
    },
    "rot": {
      "w": 0.7071069,
      "x": 0,
      "y": -0.7071067,
      "z": 0
    },
    "color": -16777216,
    "materialId": 0,
    "type": "1x4",
    "usingNewColor": true,
    "user": "d7d0daee75a94084d9a5d3d9aa78ba8e"
  },
  {
    "pos": {
      "x": 0.5083568,
      "y": 0.757232,
      "z": -1.782902
    },
    "rot": {
      "w": -4.371139e-8,
      "x": 0,
      "y": 1,
      "z": 0
    },
    "color": -16777216,
    "materialId": 0,
    "type": "1x3Slope",
    "usingNewColor": true,
    "user": "d7d0daee75a94084d9a5d3d9aa78ba8e"
  },
  {
    "pos": {
      "x": 0.3681701,
      "y": 0.856774,
      "z": 3.275773
    },
    "rot": {
      "w": 0.5000001,
      "x": -0.5000001,
      "y": -0.4999999,
      "z": 0.5
    },
    "color": -65536,
    "materialId": 0,
    "type": "2x2Tile",
    "usingNewColor": true,
    "user": "d7d0daee75a94084d9a5d3d9aa78ba8e"
  },
  {
    "pos": {
      "x": 0.3681687,
      "y": 0.8567738,
      "z": 3.804753
    },
    "rot": {
      "w": -6.181724e-8,
      "x": 0,
      "y": 0.7071068,
      "z": 0.7071068
    },
    "color": -16777216,
    "materialId": 0,
    "type": "2x2Tile",
    "usingNewColor": true,
    "user": "d7d0daee75a94084d9a5d3d9aa78ba8e"
  },
  {
    "pos": {
      "x": 0.3681692,
      "y": 0.895872,
      "z": 3.668299
    },
    "rot": {
      "w": -0.7071068,
      "x": 0.7071068,
      "y": -6.181724e-8,
      "z": 0
    },
    "color": -16711710,
    "materialId": 0,
    "type": "1x2Tile",
    "usingNewColor": true,
    "user": "d7d0daee75a94084d9a5d3d9aa78ba8e"
  },
  {
    "pos": {
      "x": 0.3962067,
      "y": 0.757232,
      "z": 3.736526
    },
    "rot": {
      "w": -0.7071069,
      "x": 0,
      "y": 0.7071068,
      "z": 0
    },
    "color": -15592941,
    "materialId": 0,
    "type": "1x2SlopeInverted",
    "usingNewColor": true,
    "user": "d7d0daee75a94084d9a5d3d9aa78ba8e"
  },
  {
    "pos": {
      "x": 0.3680437,
      "y": 0.8243679,
      "z": -1.894953
    },
    "rot": {
      "w": 4.371139e-8,
      "x": 0,
      "y": -1,
      "z": 0
    },
    "color": -16777216,
    "materialId": 0,
    "type": "1x4Slope",
    "usingNewColor": true,
    "user": "d7d0daee75a94084d9a5d3d9aa78ba8e"
  },
  {
    "pos": {
      "x": -0.2680037,
      "y": -0.3257141,
      "z": 0.1991967
    },
    "rot": {
      "w": -0.7132736,
      "x": -0.006195452,
      "y": -0.6851623,
      "z": 0.1474961
    },
    "color": -16711710,
    "materialId": 0,
    "type": "2x2",
    "usingNewColor": true,
    "user": "d7d0daee75a94084d9a5d3d9aa78ba8e"
  },
  {
    "pos": {
      "x": 0.3681692,
      "y": 0.8915039,
      "z": 3.764564
    },
    "rot": {
      "w": -8.742278e-8,
      "x": 0,
      "y": 1,
      "z": 0
    },
    "color": -15592941,
    "materialId": 0,
    "type": "1x2",
    "usingNewColor": true,
    "user": "d7d0daee75a94084d9a5d3d9aa78ba8e"
  },
  {
    "pos": {
      "x": 0.3401315,
      "y": 0.757232,
      "z": 3.344
    },
    "rot": {
      "w": -0.7071069,
      "x": 0,
      "y": 0.7071068,
      "z": 0
    },
    "color": -65536,
    "materialId": 0,
    "type": "1x2SlopeInverted",
    "usingNewColor": true,
    "user": "d7d0daee75a94084d9a5d3d9aa78ba8e"
  },
  {
    "pos": {
      "x": 0.2279812,
      "y": 0.9364039,
      "z": -1.867015
    },
    "rot": {
      "w": -0.7071069,
      "x": 0,
      "y": 0.7071066,
      "z": 0
    },
    "color": -16777216,
    "materialId": 0,
    "type": "1x2Tile",
    "usingNewColor": true,
    "user": "d7d0daee75a94084d9a5d3d9aa78ba8e"
  },
  {
    "pos": {
      "x": 0.3681684,
      "y": 0.734996,
      "z": 3.484188
    },
    "rot": {
      "w": -1,
      "x": 0,
      "y": -8.742278e-8,
      "z": 0
    },
    "color": -6094848,
    "materialId": 0,
    "type": "1x4Tile",
    "usingNewColor": true,
    "user": "d7d0daee75a94084d9a5d3d9aa78ba8e"
  },
  {
    "pos": {
      "x": 0.368169,
      "y": 0.8243679,
      "z": 3.372039
    },
    "rot": {
      "w": -1,
      "x": 0,
      "y": -1.03316e-7,
      "z": 0
    },
    "color": -65536,
    "materialId": 0,
    "type": "1x2",
    "usingNewColor": true,
    "user": "d7d0daee75a94084d9a5d3d9aa78ba8e"
  },
  {
    "pos": {
      "x": 0.3120942,
      "y": 0.734996,
      "z": 3.568301
    },
    "rot": {
      "w": -0.7071069,
      "x": 0,
      "y": 0.7071068,
      "z": 0
    },
    "color": -6094848,
    "materialId": 0,
    "type": "2x2Tile",
    "usingNewColor": true,
    "user": "d7d0daee75a94084d9a5d3d9aa78ba8e"
  },
  {
    "pos": {
      "x": 0.3681693,
      "y": 0.8915039,
      "z": 3.708488
    },
    "rot": {
      "w": -8.742278e-8,
      "x": 0,
      "y": 1,
      "z": 0
    },
    "color": -15592941,
    "materialId": 0,
    "type": "1x2_1FaceSideStud",
    "usingNewColor": true,
    "user": "d7d0daee75a94084d9a5d3d9aa78ba8e"
  },
  {
    "pos": {
      "x": 0.3401315,
      "y": 0.757232,
      "z": 3.736526
    },
    "rot": {
      "w": -0.7071068,
      "x": 0,
      "y": -0.7071069,
      "z": 0
    },
    "color": -15592941,
    "materialId": 0,
    "type": "1x2SlopeInverted",
    "usingNewColor": true,
    "user": "d7d0daee75a94084d9a5d3d9aa78ba8e"
  },
  {
    "pos": {
      "x": 0.2279812,
      "y": 0.8243679,
      "z": -1.726827
    },
    "rot": {
      "w": 0.7071069,
      "x": 0,
      "y": -0.7071067,
      "z": 0
    },
    "color": -16777216,
    "materialId": 0,
    "type": "1x1",
    "usingNewColor": true,
    "user": "d7d0daee75a94084d9a5d3d9aa78ba8e"
  },
  {
    "pos": {
      "x": 0.3120313,
      "y": 0.757232,
      "z": -1.866915
    },
    "rot": {
      "w": -0.7071069,
      "x": 0,
      "y": 0.7071068,
      "z": 0
    },
    "color": -16777216,
    "materialId": 0,
    "type": "4x2",
    "usingNewColor": true,
    "user": "d7d0daee75a94084d9a5d3d9aa78ba8e"
  },
  {
    "pos": {
      "x": 0.3681687,
      "y": 0.895872,
      "z": 3.412228
    },
    "rot": {
      "w": -1.657813e-7,
      "x": 1.039641e-7,
      "y": 0.7071068,
      "z": 0.7071068
    },
    "color": -16717825,
    "materialId": 0,
    "type": "1x2Tile",
    "usingNewColor": true,
    "user": "d7d0daee75a94084d9a5d3d9aa78ba8e"
  },
  {
    "pos": {
      "x": 0.3681691,
      "y": 0.8243679,
      "z": 3.708488
    },
    "rot": {
      "w": 1,
      "x": 0,
      "y": 4.371139e-8,
      "z": 0
    },
    "color": -15592941,
    "materialId": 0,
    "type": "1x2",
    "usingNewColor": true,
    "user": "d7d0daee75a94084d9a5d3d9aa78ba8e"
  },
  {
    "pos": {
      "x": 0.2839313,
      "y": 0.8915039,
      "z": -1.782903
    },
    "rot": {
      "w": 0.7071069,
      "x": 0,
      "y": -0.7071067,
      "z": 0
    },
    "color": -16777216,
    "materialId": 0,
    "type": "1x1",
    "usingNewColor": true,
    "user": "d7d0daee75a94084d9a5d3d9aa78ba8e"
  },
  {
    "pos": {
      "x": 0.2279813,
      "y": 0.757232,
      "z": -1.867015
    },
    "rot": {
      "w": -0.7071069,
      "x": 0,
      "y": 0.7071068,
      "z": 0
    },
    "color": -16777216,
    "materialId": 0,
    "type": "1x4",
    "usingNewColor": true,
    "user": "d7d0daee75a94084d9a5d3d9aa78ba8e"
  },
  {
    "pos": {
      "x": 0.5363947,
      "y": 0.757232,
      "z": -1.895053
    },
    "rot": {
      "w": -4.371139e-8,
      "x": 0,
      "y": 1,
      "z": 0
    },
    "color": -16777216,
    "materialId": 0,
    "type": "1x4Slope",
    "usingNewColor": true,
    "user": "d7d0daee75a94084d9a5d3d9aa78ba8e"
  },
  {
    "pos": {
      "x": 0.3681699,
      "y": 0.9363679,
      "z": 3.344002
    },
    "rot": {
      "w": 0.7071071,
      "x": 0,
      "y": -0.7071066,
      "z": 0
    },
    "color": -44032,
    "materialId": 0,
    "type": "2x2Tile",
    "usingNewColor": true,
    "user": "d7d0daee75a94084d9a5d3d9aa78ba8e"
  },
  {
    "pos": {
      "x": 0.2839315,
      "y": 0.8915039,
      "z": -1.950927
    },
    "rot": {
      "w": 0.7071069,
      "x": 0,
      "y": -0.7071067,
      "z": 0
    },
    "color": -16777216,
    "materialId": 0,
    "type": "1x1",
    "usingNewColor": true,
    "user": "d7d0daee75a94084d9a5d3d9aa78ba8e"
  },
  {
    "pos": {
      "x": 0.2279812,
      "y": 0.8915039,
      "z": -1.951126
    },
    "rot": {
      "w": 0.7071069,
      "x": 0,
      "y": -0.7071067,
      "z": 0
    },
    "color": -16777216,
    "materialId": 0,
    "type": "1x3Slope",
    "usingNewColor": true,
    "user": "d7d0daee75a94084d9a5d3d9aa78ba8e"
  },
  {
    "pos": {
      "x": 0.3680442,
      "y": 0.8243679,
      "z": -1.950927
    },
    "rot": {
      "w": 4.371139e-8,
      "x": 0,
      "y": -1,
      "z": 0
    },
    "color": -16777216,
    "materialId": 0,
    "type": "1x4Slope",
    "usingNewColor": true,
    "user": "d7d0daee75a94084d9a5d3d9aa78ba8e"
  },
  {
    "pos": {
      "x": 0.3681689,
      "y": 0.8915039,
      "z": 3.372039
    },
    "rot": {
      "w": -1,
      "x": 0,
      "y": -1.907388e-7,
      "z": 0
    },
    "color": -44032,
    "materialId": 0,
    "type": "1x2_1FaceSideStud",
    "usingNewColor": true,
    "user": "d7d0daee75a94084d9a5d3d9aa78ba8e"
  }
]