[
  {
    "pos": {
      "x": 0.7605956,
      "y": 0.757232,
      "z": -1.082025
    },
    "rot": {
      "w": -4.371139e-8,
      "x": 0,
      "y": 1,
      "z": 0
    },
    "color": -9535771,
    "materialId": 0,
    "type": "4x2",
    "usingNewColor": true,
    "user": "70aa1947f33b89fd8414aacaf032f215"
  },
  {
    "pos": {
      "x": 0.536495,
      "y": 0.757232,
      "z": -2.764154
    },
    "rot": {
      "w": -1,
      "x": 0,
      "y": -8.742278e-8,
      "z": 0
    },
    "color": -9535771,
    "materialId": 0,
    "type": "2x8",
    "usingNewColor": true,
    "user": "70aa1947f33b89fd8414aacaf032f215"
  },
  {
    "pos": {
      "x": 0.5362951,
      "y": 0.757232,
      "z": -1.082026
    },
    "rot": {
      "w": -4.371139e-8,
      "x": 0,
      "y": 1,
      "z": 0
    },
    "color": -9535771,
    "materialId": 0,
    "type": "4x2",
    "usingNewColor": true,
    "user": "70aa1947f33b89fd8414aacaf032f215"
  },
  {
    "pos": {
      "x": 0.03181878,
      "y": 0.757232,
      "z": -2.764154
    },
    "rot": {
      "w": -1,
      "x": 0,
      "y": -8.742278e-8,
      "z": 0
    },
    "color": -9535771,
    "materialId": 0,
    "type": "2x8",
    "usingNewColor": true,
    "user": "70aa1947f33b89fd8414aacaf032f215"
  },
  {
    "pos": {
      "x": -0.2486574,
      "y": 0.8243679,
      "z": -2.792129
    },
    "rot": {
      "w": -1,
      "x": 0,
      "y": -1.748456e-7,
      "z": 0
    },
    "color": -9535771,
    "materialId": 0,
    "type": "1x4Masonry",
    "usingNewColor": true,
    "user": "70aa1947f33b89fd8414aacaf032f215"
  },
  {
    "pos": {
      "x": -0.7530328,
      "y": 0.8243679,
      "z": -2.79213
    },
    "rot": {
      "w": -1,
      "x": 0,
      "y": -1.748456e-7,
      "z": 0
    },
    "color": -9535771,
    "materialId": 0,
    "type": "1x2Masonry",
    "usingNewColor": true,
    "user": "70aa1947f33b89fd8414aacaf032f215"
  },
  {
    "pos": {
      "x": 0.8168327,
      "y": 0.757232,
      "z": -2.14749
    },
    "rot": {
      "w": -0.7071068,
      "x": 0,
      "y": -0.7071069,
      "z": 0
    },
    "color": -9535771,
    "materialId": 0,
    "type": "2x8",
    "usingNewColor": true,
    "user": "70aa1947f33b89fd8414aacaf032f215"
  },
  {
    "pos": {
      "x": -0.6410832,
      "y": 0.8243679,
      "z": -2.79213
    },
    "rot": {
      "w": -1,
      "x": 0,
      "y": -1.748456e-7,
      "z": 0
    },
    "color": -9535771,
    "materialId": 0,
    "type": "1x2Masonry",
    "usingNewColor": true,
    "user": "70aa1947f33b89fd8414aacaf032f215"
  },
  {
    "pos": {
      "x": -0.8933963,
      "y": 0.8243679,
      "z": -2.484041
    },
    "rot": {
      "w": -0.7071066,
      "x": 0,
      "y": -0.7071069,
      "z": 0
    },
    "color": -9535771,
    "materialId": 0,
    "type": "1x4Masonry",
    "usingNewColor": true,
    "user": "70aa1947f33b89fd8414aacaf032f215"
  },
  {
    "pos": {
      "x": 0.1998439,
      "y": 0.757232,
      "z": -1.082026
    },
    "rot": {
      "w": -4.371139e-8,
      "x": 0,
      "y": 1,
      "z": 0
    },
    "color": -9535771,
    "materialId": 0,
    "type": "2x8",
    "usingNewColor": true,
    "user": "70aa1947f33b89fd8414aacaf032f215"
  },
  {
    "pos": {
      "x": -0.4170837,
      "y": 0.8243679,
      "z": -2.79213
    },
    "rot": {
      "w": -1,
      "x": 0,
      "y": -1.748456e-7,
      "z": 0
    },
    "color": -9535771,
    "materialId": 0,
    "type": "1x2Masonry",
    "usingNewColor": true,
    "user": "70aa1947f33b89fd8414aacaf032f215"
  },
  {
    "pos": {
      "x": 0.8167077,
      "y": 0.757232,
      "z": -2.595892
    },
    "rot": {
      "w": -0.7071069,
      "x": 0,
      "y": 0.7071068,
      "z": 0
    },
    "color": -9535771,
    "materialId": 0,
    "type": "2x8",
    "usingNewColor": true,
    "user": "70aa1947f33b89fd8414aacaf032f215"
  },
  {
    "pos": {
      "x": 0.816708,
      "y": 0.757232,
      "z": -1.306165
    },
    "rot": {
      "w": -0.7071069,
      "x": 0,
      "y": 0.7071068,
      "z": 0
    },
    "color": -9535771,
    "materialId": 0,
    "type": "2x6",
    "usingNewColor": true,
    "user": "70aa1947f33b89fd8414aacaf032f215"
  },
  {
    "pos": {
      "x": -0.5290334,
      "y": 0.8243679,
      "z": -2.79213
    },
    "rot": {
      "w": -1,
      "x": 0,
      "y": -1.748456e-7,
      "z": 0
    },
    "color": -9535771,
    "materialId": 0,
    "type": "1x2Masonry",
    "usingNewColor": true,
    "user": "70aa1947f33b89fd8414aacaf032f215"
  },
  {
    "pos": {
      "x": 0.8167077,
      "y": 0.757232,
      "z": -1.69869
    },
    "rot": {
      "w": -0.7071069,
      "x": 0,
      "y": 0.7071068,
      "z": 0
    },
    "color": -9535771,
    "materialId": 0,
    "type": "2x8",
    "usingNewColor": true,
    "user": "70aa1947f33b89fd8414aacaf032f215"
  },
  {
    "pos": {
      "x": -0.6973567,
      "y": 0.757232,
      "z": -1.082025
    },
    "rot": {
      "w": -4.371139e-8,
      "x": 0,
      "y": 1,
      "z": 0
    },
    "color": -9535771,
    "materialId": 0,
    "type": "2x8",
    "usingNewColor": true,
    "user": "70aa1947f33b89fd8414aacaf032f215"
  },
  {
    "pos": {
      "x": -0.5850082,
      "y": 0.757232,
      "z": -2.764155
    },
    "rot": {
      "w": -1,
      "x": 0,
      "y": -8.742278e-8,
      "z": 0
    },
    "color": -9535771,
    "materialId": 0,
    "type": "2x8",
    "usingNewColor": true,
    "user": "70aa1947f33b89fd8414aacaf032f215"
  },
  {
    "pos": {
      "x": -0.8374469,
      "y": 0.8243679,
      "z": -2.764015
    },
    "rot": {
      "w": -0.7071066,
      "x": 0,
      "y": -0.7071069,
      "z": 0
    },
    "color": -9535771,
    "materialId": 0,
    "type": "1x2Masonry",
    "usingNewColor": true,
    "user": "70aa1947f33b89fd8414aacaf032f215"
  },
  {
    "pos": {
      "x": -0.8655463,
      "y": 0.757232,
      "z": -1.810841
    },
    "rot": {
      "w": -0.7071069,
      "x": 0,
      "y": 0.7071068,
      "z": 0
    },
    "color": -9535771,
    "materialId": 0,
    "type": "2x8",
    "usingNewColor": true,
    "user": "70aa1947f33b89fd8414aacaf032f215"
  },
  {
    "pos": {
      "x": -0.8654221,
      "y": 0.757232,
      "z": -2.203564
    },
    "rot": {
      "w": -0.7071068,
      "x": 0,
      "y": -0.7071069,
      "z": 0
    },
    "color": -9535771,
    "materialId": 0,
    "type": "2x6",
    "usingNewColor": true,
    "user": "70aa1947f33b89fd8414aacaf032f215"
  },
  {
    "pos": {
      "x": -0.8933968,
      "y": 0.8243679,
      "z": -2.259538
    },
    "rot": {
      "w": -0.7071066,
      "x": 0,
      "y": -0.7071069,
      "z": 0
    },
    "color": -9535771,
    "materialId": 0,
    "type": "1x4Masonry",
    "usingNewColor": true,
    "user": "70aa1947f33b89fd8414aacaf032f215"
  },
  {
    "pos": {
      "x": -0.2487496,
      "y": 0.757232,
      "z": -1.082023
    },
    "rot": {
      "w": -4.371139e-8,
      "x": 0,
      "y": 1,
      "z": 0
    },
    "color": -9535771,
    "materialId": 0,
    "type": "2x8",
    "usingNewColor": true,
    "user": "70aa1947f33b89fd8414aacaf032f215"
  },
  {
    "pos": {
      "x": -0.8654215,
      "y": 0.757232,
      "z": -1.362438
    },
    "rot": {
      "w": -0.7071068,
      "x": 0,
      "y": -0.7071069,
      "z": 0
    },
    "color": -9535771,
    "materialId": 0,
    "type": "2x8",
    "usingNewColor": true,
    "user": "70aa1947f33b89fd8414aacaf032f215"
  },
  {
    "pos": {
      "x": -0.8933963,
      "y": 0.8243679,
      "z": -2.70804
    },
    "rot": {
      "w": -0.7071066,
      "x": 0,
      "y": -0.7071069,
      "z": 0
    },
    "color": -9535771,
    "materialId": 0,
    "type": "1x4Masonry",
    "usingNewColor": true,
    "user": "70aa1947f33b89fd8414aacaf032f215"
  },
  {
    "pos": {
      "x": -0.8654216,
      "y": 0.757232,
      "z": -2.596091
    },
    "rot": {
      "w": -0.7071068,
      "x": 0,
      "y": -0.7071069,
      "z": 0
    },
    "color": -9535771,
    "materialId": 0,
    "type": "2x8",
    "usingNewColor": true,
    "user": "70aa1947f33b89fd8414aacaf032f215"
  },
  {
    "pos": {
      "x": -0.276695,
      "y": 0.757232,
      "z": -2.764154
    },
    "rot": {
      "w": -1,
      "x": 0,
      "y": -8.742278e-8,
      "z": 0
    },
    "color": -9535771,
    "materialId": 0,
    "type": "2x3",
    "usingNewColor": true,
    "user": "70aa1947f33b89fd8414aacaf032f215"
  }
]