[
  {
    "pos": {
      "x": -0.3326446,
      "y": 0.802132,
      "z": -2.063478
    },
    "rot": {
      "w": -0.7071066,
      "x": 0,
      "y": -0.7071069,
      "z": 0
    },
    "color": -3855316,
    "materialId": 0,
    "type": "FlatPlant",
    "usingNewColor": true,
    "user": "866f58c7e2dbe62c376ca77f2c0afd0c"
  },
  {
    "pos": {
      "x": 0.2561437,
      "y": 1.227184,
      "z": -1.979273
    },
    "rot": {
      "w": 6.079713e-7,
      "x": 0,
      "y": -1,
      "z": 0
    },
    "color": -9667359,
    "materialId": 0,
    "type": "2x2Slope",
    "usingNewColor": true,
    "user": "866f58c7e2dbe62c376ca77f2c0afd0c"
  },
  {
    "pos": {
      "x": 0.1993854,
      "y": 1.160048,
      "z": -2.147512
    },
    "rot": {
      "w": 0.7071069,
      "x": 0,
      "y": -0.7071067,
      "z": 0
    },
    "color": -9667359,
    "materialId": 0,
    "type": "2x2Slope",
    "usingNewColor": true,
    "user": "866f58c7e2dbe62c376ca77f2c0afd0c"
  },
  {
    "pos": {
      "x": 0.3682941,
      "y": 1.092912,
      "z": -1.867175
    },
    "rot": {
      "w": 5.205485e-7,
      "x": 0,
      "y": -1,
      "z": 0
    },
    "color": -9535771,
    "materialId": 0,
    "type": "2x2Slope",
    "usingNewColor": true,
    "user": "866f58c7e2dbe62c376ca77f2c0afd0c"
  },
  {
    "pos": {
      "x": -0.0805053,
      "y": 0.8915039,
      "z": -2.203526
    },
    "rot": {
      "w": 1.311342e-7,
      "x": 0,
      "y": -1,
      "z": 0
    },
    "color": -9535771,
    "materialId": 0,
    "type": "2x6",
    "usingNewColor": true,
    "user": "866f58c7e2dbe62c376ca77f2c0afd0c"
  },
  {
    "pos": {
      "x": -0.1925201,
      "y": 0.757232,
      "z": -2.147489
    },
    "rot": {
      "w": -0.7071068,
      "x": 0,
      "y": -0.7071069,
      "z": 0
    },
    "color": -9535771,
    "materialId": 0,
    "type": "4x2",
    "usingNewColor": true,
    "user": "866f58c7e2dbe62c376ca77f2c0afd0c"
  },
  {
    "pos": {
      "x": -0.08050664,
      "y": 0.8915039,
      "z": -1.642875
    },
    "rot": {
      "w": 1.311342e-7,
      "x": 0,
      "y": -1,
      "z": 0
    },
    "color": -9535771,
    "materialId": 0,
    "type": "2x6",
    "usingNewColor": true,
    "user": "866f58c7e2dbe62c376ca77f2c0afd0c"
  },
  {
    "pos": {
      "x": 0.3682308,
      "y": 0.8243679,
      "z": -1.923187
    },
    "rot": {
      "w": -0.7071066,
      "x": 0,
      "y": -0.7071069,
      "z": 0
    },
    "color": -9535771,
    "materialId": 0,
    "type": "2x8",
    "usingNewColor": true,
    "user": "866f58c7e2dbe62c376ca77f2c0afd0c"
  },
  {
    "pos": {
      "x": 0.1433859,
      "y": 1.227184,
      "z": -2.091436
    },
    "rot": {
      "w": 0.7071069,
      "x": 0,
      "y": -0.7071067,
      "z": 0
    },
    "color": -9667359,
    "materialId": 0,
    "type": "2x2Slope",
    "usingNewColor": true,
    "user": "866f58c7e2dbe62c376ca77f2c0afd0c"
  },
  {
    "pos": {
      "x": 0.08766837,
      "y": 1.406384,
      "z": -1.923436
    },
    "rot": {
      "w": -1,
      "x": 0,
      "y": -3.715369e-7,
      "z": 0
    },
    "color": -8422657,
    "materialId": 0,
    "type": "2x2Plate1Stud",
    "usingNewColor": true,
    "user": "866f58c7e2dbe62c376ca77f2c0afd0c"
  },
  {
    "pos": {
      "x": -0.08043192,
      "y": 1.227212,
      "z": -1.979374
    },
    "rot": {
      "w": -1,
      "x": 0,
      "y": -2.781616e-7,
      "z": 0
    },
    "color": -9667359,
    "materialId": 0,
    "type": "2x2Slope",
    "usingNewColor": true,
    "user": "866f58c7e2dbe62c376ca77f2c0afd0c"
  },
  {
    "pos": {
      "x": -0.2204945,
      "y": 0.9257679,
      "z": -2.09154
    },
    "rot": {
      "w": 0.7071069,
      "x": 0,
      "y": -0.7071067,
      "z": 0
    },
    "color": -9535771,
    "materialId": 0,
    "type": "1x2Window",
    "usingNewColor": true,
    "user": "866f58c7e2dbe62c376ca77f2c0afd0c"
  },
  {
    "pos": {
      "x": 0.1161148,
      "y": 1.428592,
      "z": -1.8948
    },
    "rot": {
      "w": 1,
      "x": 0,
      "y": 5.205485e-7,
      "z": 0
    },
    "color": -8422657,
    "materialId": 0,
    "type": "1x1Pyramid",
    "usingNewColor": true,
    "user": "866f58c7e2dbe62c376ca77f2c0afd0c"
  },
  {
    "pos": {
      "x": -0.2766952,
      "y": 0.802132,
      "z": -2.119453
    },
    "rot": {
      "w": -0.7071066,
      "x": 0,
      "y": -0.7071069,
      "z": 0
    },
    "color": -65536,
    "materialId": 0,
    "type": "ThreeLeafedPlant",
    "usingNewColor": true,
    "user": "866f58c7e2dbe62c376ca77f2c0afd0c"
  },
  {
    "pos": {
      "x": -0.0245264,
      "y": 1.025776,
      "z": -2.203524
    },
    "rot": {
      "w": 1.311342e-7,
      "x": 0,
      "y": -1,
      "z": 0
    },
    "color": -9535771,
    "materialId": 0,
    "type": "2x8",
    "usingNewColor": true,
    "user": "866f58c7e2dbe62c376ca77f2c0afd0c"
  },
  {
    "pos": {
      "x": -0.2766952,
      "y": 0.802132,
      "z": -1.670852
    },
    "rot": {
      "w": -1,
      "x": 0,
      "y": -1.03316e-7,
      "z": 0
    },
    "color": -3855316,
    "materialId": 0,
    "type": "ThreeLeafedPlant",
    "usingNewColor": true,
    "user": "866f58c7e2dbe62c376ca77f2c0afd0c"
  },
  {
    "pos": {
      "x": 0.08789381,
      "y": 0.757232,
      "z": -1.642651
    },
    "rot": {
      "w": -1,
      "x": 0,
      "y": -8.742278e-8,
      "z": 0
    },
    "color": -9535771,
    "materialId": 0,
    "type": "2x8",
    "usingNewColor": true,
    "user": "866f58c7e2dbe62c376ca77f2c0afd0c"
  },
  {
    "pos": {
      "x": -0.1925822,
      "y": 1.09294,
      "z": -2.091475
    },
    "rot": {
      "w": -1,
      "x": 0,
      "y": -1.03316e-7,
      "z": 0
    },
    "color": -9535771,
    "materialId": 0,
    "type": "2x2Slope",
    "usingNewColor": true,
    "user": "866f58c7e2dbe62c376ca77f2c0afd0c"
  },
  {
    "pos": {
      "x": -0.02435678,
      "y": 1.294348,
      "z": -1.923374
    },
    "rot": {
      "w": -1,
      "x": 0,
      "y": -3.655844e-7,
      "z": 0
    },
    "color": -9667359,
    "materialId": 0,
    "type": "2x2Slope",
    "usingNewColor": true,
    "user": "866f58c7e2dbe62c376ca77f2c0afd0c"
  },
  {
    "pos": {
      "x": -0.1924572,
      "y": 0.8243679,
      "z": -1.754925
    },
    "rot": {
      "w": 1.03316e-7,
      "x": 0,
      "y": -1,
      "z": 0
    },
    "color": -9535771,
    "materialId": 0,
    "type": "2x2",
    "usingNewColor": true,
    "user": "866f58c7e2dbe62c376ca77f2c0afd0c"
  },
  {
    "pos": {
      "x": 0.1999469,
      "y": 0.8243679,
      "z": -1.64265
    },
    "rot": {
      "w": -1.311342e-7,
      "x": 0,
      "y": 1,
      "z": 0
    },
    "color": -9535771,
    "materialId": 0,
    "type": "2x8",
    "usingNewColor": true,
    "user": "866f58c7e2dbe62c376ca77f2c0afd0c"
  },
  {
    "pos": {
      "x": 0.2559236,
      "y": 0.8915039,
      "z": -1.64265
    },
    "rot": {
      "w": 1.311342e-7,
      "x": 0,
      "y": -1,
      "z": 0
    },
    "color": -9535771,
    "materialId": 0,
    "type": "2x6",
    "usingNewColor": true,
    "user": "866f58c7e2dbe62c376ca77f2c0afd0c"
  },
  {
    "pos": {
      "x": 0.2840564,
      "y": 0.824632,
      "z": -1.754739
    },
    "rot": {
      "w": -0.7071066,
      "x": 0,
      "y": -0.7071071,
      "z": 0
    },
    "color": -9535771,
    "materialId": 0,
    "type": "1x2Tile",
    "usingNewColor": true,
    "user": "866f58c7e2dbe62c376ca77f2c0afd0c"
  },
  {
    "pos": {
      "x": 0.3680772,
      "y": 1.092912,
      "z": -1.642648
    },
    "rot": {
      "w": 1.311342e-7,
      "x": 0,
      "y": -1,
      "z": 0
    },
    "color": -9667359,
    "materialId": 0,
    "type": "2x2CornerSlope",
    "usingNewColor": true,
    "user": "866f58c7e2dbe62c376ca77f2c0afd0c"
  },
  {
    "pos": {
      "x": -0.2766952,
      "y": 0.802132,
      "z": -1.614877
    },
    "rot": {
      "w": -1,
      "x": 0,
      "y": -1.03316e-7,
      "z": 0
    },
    "color": -3855316,
    "materialId": 0,
    "type": "ThreeLeafedPlant",
    "usingNewColor": true,
    "user": "866f58c7e2dbe62c376ca77f2c0afd0c"
  },
  {
    "pos": {
      "x": 0.2001311,
      "y": 1.29432,
      "z": -2.035286
    },
    "rot": {
      "w": 0.7071072,
      "x": 0,
      "y": -0.7071064,
      "z": 0
    },
    "color": -9667359,
    "materialId": 0,
    "type": "2x2CornerSlope",
    "usingNewColor": true,
    "user": "866f58c7e2dbe62c376ca77f2c0afd0c"
  },
  {
    "pos": {
      "x": 0.3120016,
      "y": 1.025776,
      "z": -1.642649
    },
    "rot": {
      "w": 1.311342e-7,
      "x": 0,
      "y": -1,
      "z": 0
    },
    "color": -9535771,
    "materialId": 0,
    "type": "4x2",
    "usingNewColor": true,
    "user": "866f58c7e2dbe62c376ca77f2c0afd0c"
  },
  {
    "pos": {
      "x": 0.3677138,
      "y": 1.092912,
      "z": -2.20359
    },
    "rot": {
      "w": 0.7071069,
      "x": 0,
      "y": -0.7071067,
      "z": 0
    },
    "color": -9535771,
    "materialId": 0,
    "type": "2x2CornerSlope",
    "usingNewColor": true,
    "user": "866f58c7e2dbe62c376ca77f2c0afd0c"
  },
  {
    "pos": {
      "x": -0.7533334,
      "y": 0.734996,
      "z": -2.427766
    },
    "rot": {
      "w": -4.371139e-8,
      "x": 0,
      "y": 1,
      "z": 0
    },
    "color": -9535771,
    "materialId": 0,
    "type": "2x4Plate",
    "usingNewColor": true,
    "user": "866f58c7e2dbe62c376ca77f2c0afd0c"
  },
  {
    "pos": {
      "x": -0.2766952,
      "y": 0.802132,
      "z": -2.231503
    },
    "rot": {
      "w": -0.7071066,
      "x": 0,
      "y": -0.7071069,
      "z": 0
    },
    "color": -3855316,
    "materialId": 0,
    "type": "ThreeLeafedPlant",
    "usingNewColor": true,
    "user": "866f58c7e2dbe62c376ca77f2c0afd0c"
  },
  {
    "pos": {
      "x": 0.3122186,
      "y": 1.160048,
      "z": -1.923275
    },
    "rot": {
      "w": 6.079713e-7,
      "x": 0,
      "y": -1,
      "z": 0
    },
    "color": -9667359,
    "materialId": 0,
    "type": "2x2Slope",
    "usingNewColor": true,
    "user": "866f58c7e2dbe62c376ca77f2c0afd0c"
  },
  {
    "pos": {
      "x": -0.1364818,
      "y": 0.8243679,
      "z": -2.203526
    },
    "rot": {
      "w": 1.03316e-7,
      "x": 0,
      "y": -1,
      "z": 0
    },
    "color": -9535771,
    "materialId": 0,
    "type": "4x2",
    "usingNewColor": true,
    "user": "866f58c7e2dbe62c376ca77f2c0afd0c"
  },
  {
    "pos": {
      "x": -0.1925203,
      "y": 0.757232,
      "z": -1.698887
    },
    "rot": {
      "w": -0.7071068,
      "x": 0,
      "y": -0.7071069,
      "z": 0
    },
    "color": -9535771,
    "materialId": 0,
    "type": "4x2",
    "usingNewColor": true,
    "user": "866f58c7e2dbe62c376ca77f2c0afd0c"
  },
  {
    "pos": {
      "x": -0.2766952,
      "y": 0.802132,
      "z": -1.726927
    },
    "rot": {
      "w": -1,
      "x": 0,
      "y": -1.03316e-7,
      "z": 0
    },
    "color": -3855316,
    "materialId": 0,
    "type": "ThreeLeafedPlant",
    "usingNewColor": true,
    "user": "866f58c7e2dbe62c376ca77f2c0afd0c"
  },
  {
    "pos": {
      "x": 0.08769411,
      "y": 0.757232,
      "z": -2.203528
    },
    "rot": {
      "w": -4.371139e-8,
      "x": 0,
      "y": 1,
      "z": 0
    },
    "color": -9535771,
    "materialId": 0,
    "type": "2x8",
    "usingNewColor": true,
    "user": "866f58c7e2dbe62c376ca77f2c0afd0c"
  },
  {
    "pos": {
      "x": 0.03165611,
      "y": 1.361484,
      "z": -1.867361
    },
    "rot": {
      "w": -0.7071065,
      "x": 0,
      "y": -0.7071071,
      "z": 0
    },
    "color": -9667359,
    "materialId": 0,
    "type": "2x2CornerSlope",
    "usingNewColor": true,
    "user": "866f58c7e2dbe62c376ca77f2c0afd0c"
  },
  {
    "pos": {
      "x": -0.136507,
      "y": 1.160076,
      "z": -1.811475
    },
    "rot": {
      "w": -1,
      "x": 0,
      "y": -1.907388e-7,
      "z": 0
    },
    "color": -9667359,
    "materialId": 0,
    "type": "2x2Slope",
    "usingNewColor": true,
    "user": "866f58c7e2dbe62c376ca77f2c0afd0c"
  },
  {
    "pos": {
      "x": 0.3682947,
      "y": 1.092912,
      "z": -2.091173
    },
    "rot": {
      "w": 5.205485e-7,
      "x": 0,
      "y": -1,
      "z": 0
    },
    "color": -9535771,
    "materialId": 0,
    "type": "2x2Slope",
    "usingNewColor": true,
    "user": "866f58c7e2dbe62c376ca77f2c0afd0c"
  },
  {
    "pos": {
      "x": -0.2766952,
      "y": 0.802132,
      "z": -1.782902
    },
    "rot": {
      "w": -0.7071066,
      "x": 0,
      "y": -0.7071069,
      "z": 0
    },
    "color": -3855316,
    "materialId": 0,
    "type": "ThreeLeafedPlant",
    "usingNewColor": true,
    "user": "866f58c7e2dbe62c376ca77f2c0afd0c"
  },
  {
    "pos": {
      "x": -0.02467586,
      "y": 1.29432,
      "z": -2.035424
    },
    "rot": {
      "w": 1,
      "x": 0,
      "y": 4.371139e-8,
      "z": 0
    },
    "color": -9667359,
    "materialId": 0,
    "type": "2x2CornerSlope",
    "usingNewColor": true,
    "user": "866f58c7e2dbe62c376ca77f2c0afd0c"
  },
  {
    "pos": {
      "x": 0.2000396,
      "y": 1.160048,
      "z": -1.698661
    },
    "rot": {
      "w": -0.7071066,
      "x": 0,
      "y": -0.7071071,
      "z": 0
    },
    "color": -9667359,
    "materialId": 0,
    "type": "2x2Slope",
    "usingNewColor": true,
    "user": "866f58c7e2dbe62c376ca77f2c0afd0c"
  },
  {
    "pos": {
      "x": -0.3326446,
      "y": 0.802132,
      "z": -1.670852
    },
    "rot": {
      "w": -0.7071066,
      "x": 0,
      "y": -0.7071069,
      "z": 0
    },
    "color": -65536,
    "materialId": 0,
    "type": "FlatPlant",
    "usingNewColor": true,
    "user": "866f58c7e2dbe62c376ca77f2c0afd0c"
  },
  {
    "pos": {
      "x": -0.02441941,
      "y": 1.294348,
      "z": -1.811412
    },
    "rot": {
      "w": -0.7071066,
      "x": 0,
      "y": -0.7071071,
      "z": 0
    },
    "color": -9667359,
    "materialId": 0,
    "type": "2x2CornerSlope",
    "usingNewColor": true,
    "user": "866f58c7e2dbe62c376ca77f2c0afd0c"
  },
  {
    "pos": {
      "x": -0.1364804,
      "y": 0.9586399,
      "z": -1.642874
    },
    "rot": {
      "w": 1.311342e-7,
      "x": 0,
      "y": -1,
      "z": 0
    },
    "color": -9535771,
    "materialId": 0,
    "type": "4x2",
    "usingNewColor": true,
    "user": "866f58c7e2dbe62c376ca77f2c0afd0c"
  },
  {
    "pos": {
      "x": -0.1925201,
      "y": 1.025804,
      "z": -1.923486
    },
    "rot": {
      "w": -0.7071067,
      "x": 0,
      "y": -0.7071069,
      "z": 0
    },
    "color": -9535771,
    "materialId": 0,
    "type": "2x8",
    "usingNewColor": true,
    "user": "866f58c7e2dbe62c376ca77f2c0afd0c"
  },
  {
    "pos": {
      "x": -0.08043189,
      "y": 1.227212,
      "z": -1.867425
    },
    "rot": {
      "w": -1,
      "x": 0,
      "y": -2.781616e-7,
      "z": 0
    },
    "color": -9667359,
    "materialId": 0,
    "type": "2x2Slope",
    "usingNewColor": true,
    "user": "866f58c7e2dbe62c376ca77f2c0afd0c"
  },
  {
    "pos": {
      "x": 0.1440549,
      "y": 1.361456,
      "z": -1.979337
    },
    "rot": {
      "w": 0.7071072,
      "x": 0,
      "y": -0.7071064,
      "z": 0
    },
    "color": -9667359,
    "materialId": 0,
    "type": "2x2CornerSlope",
    "usingNewColor": true,
    "user": "866f58c7e2dbe62c376ca77f2c0afd0c"
  },
  {
    "pos": {
      "x": -0.02442923,
      "y": 1.025776,
      "z": -1.642874
    },
    "rot": {
      "w": 1.311342e-7,
      "x": 0,
      "y": -1,
      "z": 0
    },
    "color": -9535771,
    "materialId": 0,
    "type": "2x8",
    "usingNewColor": true,
    "user": "866f58c7e2dbe62c376ca77f2c0afd0c"
  },
  {
    "pos": {
      "x": -0.3326446,
      "y": 0.802132,
      "z": -2.119453
    },
    "rot": {
      "w": -0.7071066,
      "x": 0,
      "y": -0.7071069,
      "z": 0
    },
    "color": -3855316,
    "materialId": 0,
    "type": "FlatPlant",
    "usingNewColor": true,
    "user": "866f58c7e2dbe62c376ca77f2c0afd0c"
  },
  {
    "pos": {
      "x": 0.08766837,
      "y": 1.45112,
      "z": -1.923436
    },
    "rot": {
      "w": -0.7071065,
      "x": 0,
      "y": -0.7071071,
      "z": 0
    },
    "color": -8422657,
    "materialId": 0,
    "type": "1x1Pyramid",
    "usingNewColor": true,
    "user": "866f58c7e2dbe62c376ca77f2c0afd0c"
  },
  {
    "pos": {
      "x": 0.3681696,
      "y": 0.757232,
      "z": -2.203528
    },
    "rot": {
      "w": -4.371139e-8,
      "x": 0,
      "y": 1,
      "z": 0
    },
    "color": -9535771,
    "materialId": 0,
    "type": "2x2",
    "usingNewColor": true,
    "user": "866f58c7e2dbe62c376ca77f2c0afd0c"
  },
  {
    "pos": {
      "x": 0.0874359,
      "y": 1.160048,
      "z": -2.147512
    },
    "rot": {
      "w": 0.7071069,
      "x": 0,
      "y": -0.7071067,
      "z": 0
    },
    "color": -9667359,
    "materialId": 0,
    "type": "2x2Slope",
    "usingNewColor": true,
    "user": "866f58c7e2dbe62c376ca77f2c0afd0c"
  },
  {
    "pos": {
      "x": -0.08062644,
      "y": 1.227184,
      "z": -2.0915
    },
    "rot": {
      "w": 1,
      "x": 0,
      "y": 4.371139e-8,
      "z": 0
    },
    "color": -9667359,
    "materialId": 0,
    "type": "2x2CornerSlope",
    "usingNewColor": true,
    "user": "866f58c7e2dbe62c376ca77f2c0afd0c"
  },
  {
    "pos": {
      "x": 0.3681695,
      "y": 0.757232,
      "z": -1.642777
    },
    "rot": {
      "w": -4.371139e-8,
      "x": 0,
      "y": 1,
      "z": 0
    },
    "color": -9535771,
    "materialId": 0,
    "type": "2x2",
    "usingNewColor": true,
    "user": "866f58c7e2dbe62c376ca77f2c0afd0c"
  },
  {
    "pos": {
      "x": -0.02434138,
      "y": 1.160048,
      "z": -1.698886
    },
    "rot": {
      "w": -0.7071066,
      "x": 0,
      "y": -0.7071071,
      "z": 0
    },
    "color": -9667359,
    "materialId": 0,
    "type": "2x2Slope",
    "usingNewColor": true,
    "user": "866f58c7e2dbe62c376ca77f2c0afd0c"
  },
  {
    "pos": {
      "x": 0.2000684,
      "y": 1.29432,
      "z": -1.923324
    },
    "rot": {
      "w": 6.079713e-7,
      "x": 0,
      "y": -1,
      "z": 0
    },
    "color": -9667359,
    "materialId": 0,
    "type": "2x2Slope",
    "usingNewColor": true,
    "user": "866f58c7e2dbe62c376ca77f2c0afd0c"
  },
  {
    "pos": {
      "x": 0.3682939,
      "y": 1.092912,
      "z": -1.979224
    },
    "rot": {
      "w": 5.205485e-7,
      "x": 0,
      "y": -1,
      "z": 0
    },
    "color": -9535771,
    "materialId": 0,
    "type": "2x2Slope",
    "usingNewColor": true,
    "user": "866f58c7e2dbe62c376ca77f2c0afd0c"
  },
  {
    "pos": {
      "x": 0.3682951,
      "y": 1.092912,
      "z": -1.755224
    },
    "rot": {
      "w": 5.205485e-7,
      "x": 0,
      "y": -1,
      "z": 0
    },
    "color": -9535771,
    "materialId": 0,
    "type": "2x2Slope",
    "usingNewColor": true,
    "user": "866f58c7e2dbe62c376ca77f2c0afd0c"
  },
  {
    "pos": {
      "x": 0.08813965,
      "y": 1.29432,
      "z": -1.810812
    },
    "rot": {
      "w": -0.7071064,
      "x": 0,
      "y": -0.7071073,
      "z": 0
    },
    "color": -9667359,
    "materialId": 0,
    "type": "2x2Slope",
    "usingNewColor": true,
    "user": "866f58c7e2dbe62c376ca77f2c0afd0c"
  },
  {
    "pos": {
      "x": -0.3326446,
      "y": 0.802132,
      "z": -1.614877
    },
    "rot": {
      "w": -1,
      "x": 0,
      "y": -1.03316e-7,
      "z": 0
    },
    "color": -3855316,
    "materialId": 0,
    "type": "FlatPlant",
    "usingNewColor": true,
    "user": "866f58c7e2dbe62c376ca77f2c0afd0c"
  },
  {
    "pos": {
      "x": 0.2562068,
      "y": 1.227184,
      "z": -2.091236
    },
    "rot": {
      "w": 0.7071072,
      "x": 0,
      "y": -0.7071064,
      "z": 0
    },
    "color": -9667359,
    "materialId": 0,
    "type": "2x2CornerSlope",
    "usingNewColor": true,
    "user": "866f58c7e2dbe62c376ca77f2c0afd0c"
  },
  {
    "pos": {
      "x": 0.0316584,
      "y": 1.227184,
      "z": -1.754962
    },
    "rot": {
      "w": -0.7071065,
      "x": 0,
      "y": -0.7071072,
      "z": 0
    },
    "color": -9667359,
    "materialId": 0,
    "type": "2x2Slope",
    "usingNewColor": true,
    "user": "866f58c7e2dbe62c376ca77f2c0afd0c"
  },
  {
    "pos": {
      "x": -0.3046699,
      "y": 0.757232,
      "z": -1.69889
    },
    "rot": {
      "w": -0.7071068,
      "x": 0,
      "y": -0.7071069,
      "z": 0
    },
    "color": -12106462,
    "materialId": 0,
    "type": "4x2",
    "usingNewColor": true,
    "user": "866f58c7e2dbe62c376ca77f2c0afd0c"
  },
  {
    "pos": {
      "x": 0.08728623,
      "y": 1.29432,
      "z": -2.035361
    },
    "rot": {
      "w": 0.7071069,
      "x": 0,
      "y": -0.7071067,
      "z": 0
    },
    "color": -9667359,
    "materialId": 0,
    "type": "2x2Slope",
    "usingNewColor": true,
    "user": "866f58c7e2dbe62c376ca77f2c0afd0c"
  },
  {
    "pos": {
      "x": 0.1441524,
      "y": 1.361456,
      "z": -1.866825
    },
    "rot": {
      "w": 6.099555e-7,
      "x": 0,
      "y": -1,
      "z": 0
    },
    "color": -9667359,
    "materialId": 0,
    "type": "2x2CornerSlope",
    "usingNewColor": true,
    "user": "866f58c7e2dbe62c376ca77f2c0afd0c"
  },
  {
    "pos": {
      "x": 0.1440897,
      "y": 1.227184,
      "z": -1.754736
    },
    "rot": {
      "w": -0.7071065,
      "x": 0,
      "y": -0.7071072,
      "z": 0
    },
    "color": -9667359,
    "materialId": 0,
    "type": "2x2Slope",
    "usingNewColor": true,
    "user": "866f58c7e2dbe62c376ca77f2c0afd0c"
  },
  {
    "pos": {
      "x": 0.3682307,
      "y": 0.8915039,
      "z": -1.867212
    },
    "rot": {
      "w": -0.7071065,
      "x": 0,
      "y": -0.7071071,
      "z": 0
    },
    "color": -9535771,
    "materialId": 0,
    "type": "2x6",
    "usingNewColor": true,
    "user": "866f58c7e2dbe62c376ca77f2c0afd0c"
  },
  {
    "pos": {
      "x": 0.1434355,
      "y": 1.092912,
      "z": -2.203587
    },
    "rot": {
      "w": 0.7071069,
      "x": 0,
      "y": -0.7071067,
      "z": 0
    },
    "color": -9535771,
    "materialId": 0,
    "type": "2x2Slope",
    "usingNewColor": true,
    "user": "866f58c7e2dbe62c376ca77f2c0afd0c"
  },
  {
    "pos": {
      "x": -0.1925821,
      "y": 1.09294,
      "z": -1.867475
    },
    "rot": {
      "w": -1,
      "x": 0,
      "y": -1.03316e-7,
      "z": 0
    },
    "color": -9535771,
    "materialId": 0,
    "type": "2x2Slope",
    "usingNewColor": true,
    "user": "866f58c7e2dbe62c376ca77f2c0afd0c"
  },
  {
    "pos": {
      "x": 0.3122819,
      "y": 1.160048,
      "z": -2.147186
    },
    "rot": {
      "w": 0.7071072,
      "x": 0,
      "y": -0.7071064,
      "z": 0
    },
    "color": -9667359,
    "materialId": 0,
    "type": "2x2CornerSlope",
    "usingNewColor": true,
    "user": "866f58c7e2dbe62c376ca77f2c0afd0c"
  },
  {
    "pos": {
      "x": -0.1925512,
      "y": 1.092912,
      "z": -2.203524
    },
    "rot": {
      "w": -1,
      "x": 0,
      "y": -8.742278e-8,
      "z": 0
    },
    "color": -9535771,
    "materialId": 0,
    "type": "2x2CornerSlope",
    "usingNewColor": true,
    "user": "866f58c7e2dbe62c376ca77f2c0afd0c"
  },
  {
    "pos": {
      "x": 0.1997471,
      "y": 0.8243679,
      "z": -2.203528
    },
    "rot": {
      "w": 1.311342e-7,
      "x": 0,
      "y": -1,
      "z": 0
    },
    "color": -9535771,
    "materialId": 0,
    "type": "2x8",
    "usingNewColor": true,
    "user": "866f58c7e2dbe62c376ca77f2c0afd0c"
  },
  {
    "pos": {
      "x": 0.2001032,
      "y": 1.29432,
      "z": -1.81075
    },
    "rot": {
      "w": 5.205485e-7,
      "x": 0,
      "y": -1,
      "z": 0
    },
    "color": -9667359,
    "materialId": 0,
    "type": "2x2CornerSlope",
    "usingNewColor": true,
    "user": "866f58c7e2dbe62c376ca77f2c0afd0c"
  },
  {
    "pos": {
      "x": 0.3122193,
      "y": 1.160048,
      "z": -2.035223
    },
    "rot": {
      "w": 6.079713e-7,
      "x": 0,
      "y": -1,
      "z": 0
    },
    "color": -9667359,
    "materialId": 0,
    "type": "2x2Slope",
    "usingNewColor": true,
    "user": "866f58c7e2dbe62c376ca77f2c0afd0c"
  },
  {
    "pos": {
      "x": -0.080442,
      "y": 1.092912,
      "z": -1.64281
    },
    "rot": {
      "w": -0.7071067,
      "x": 0,
      "y": -0.7071069,
      "z": 0
    },
    "color": -9535771,
    "materialId": 0,
    "type": "2x2Slope",
    "usingNewColor": true,
    "user": "866f58c7e2dbe62c376ca77f2c0afd0c"
  },
  {
    "pos": {
      "x": 0.3116989,
      "y": 0.9586399,
      "z": -2.203528
    },
    "rot": {
      "w": 1.311342e-7,
      "x": 0,
      "y": -1,
      "z": 0
    },
    "color": -9535771,
    "materialId": 0,
    "type": "4x2",
    "usingNewColor": true,
    "user": "866f58c7e2dbe62c376ca77f2c0afd0c"
  },
  {
    "pos": {
      "x": 0.2556636,
      "y": 1.092912,
      "z": -2.20359
    },
    "rot": {
      "w": 0.7071069,
      "x": 0,
      "y": -0.7071067,
      "z": 0
    },
    "color": -9535771,
    "materialId": 0,
    "type": "2x2Slope",
    "usingNewColor": true,
    "user": "866f58c7e2dbe62c376ca77f2c0afd0c"
  },
  {
    "pos": {
      "x": -0.3046699,
      "y": 0.757232,
      "z": -2.147491
    },
    "rot": {
      "w": -0.7071068,
      "x": 0,
      "y": -0.7071069,
      "z": 0
    },
    "color": -12106462,
    "materialId": 0,
    "type": "4x2",
    "usingNewColor": true,
    "user": "866f58c7e2dbe62c376ca77f2c0afd0c"
  },
  {
    "pos": {
      "x": 0.08760826,
      "y": 1.160048,
      "z": -1.698886
    },
    "rot": {
      "w": -0.7071066,
      "x": 0,
      "y": -0.7071071,
      "z": 0
    },
    "color": -9667359,
    "materialId": 0,
    "type": "2x2Slope",
    "usingNewColor": true,
    "user": "866f58c7e2dbe62c376ca77f2c0afd0c"
  },
  {
    "pos": {
      "x": 0.03160821,
      "y": 1.092912,
      "z": -1.642811
    },
    "rot": {
      "w": -0.7071067,
      "x": 0,
      "y": -0.7071069,
      "z": 0
    },
    "color": -9667359,
    "materialId": 0,
    "type": "2x2Slope",
    "usingNewColor": true,
    "user": "866f58c7e2dbe62c376ca77f2c0afd0c"
  },
  {
    "pos": {
      "x": -0.1364824,
      "y": 0.8243679,
      "z": -1.642875
    },
    "rot": {
      "w": 1.03316e-7,
      "x": 0,
      "y": -1,
      "z": 0
    },
    "color": -9535771,
    "materialId": 0,
    "type": "4x2",
    "usingNewColor": true,
    "user": "866f58c7e2dbe62c376ca77f2c0afd0c"
  },
  {
    "pos": {
      "x": -0.136507,
      "y": 1.160076,
      "z": -2.035475
    },
    "rot": {
      "w": -1,
      "x": 0,
      "y": -1.907388e-7,
      "z": 0
    },
    "color": -9667359,
    "materialId": 0,
    "type": "2x2Slope",
    "usingNewColor": true,
    "user": "866f58c7e2dbe62c376ca77f2c0afd0c"
  },
  {
    "pos": {
      "x": -0.08049428,
      "y": 1.227212,
      "z": -1.755463
    },
    "rot": {
      "w": -0.7071066,
      "x": 0,
      "y": -0.707107,
      "z": 0
    },
    "color": -9667359,
    "materialId": 0,
    "type": "2x2CornerSlope",
    "usingNewColor": true,
    "user": "866f58c7e2dbe62c376ca77f2c0afd0c"
  },
  {
    "pos": {
      "x": -0.1365695,
      "y": 1.160076,
      "z": -1.699513
    },
    "rot": {
      "w": -0.7071067,
      "x": 0,
      "y": -0.7071069,
      "z": 0
    },
    "color": -9667359,
    "materialId": 0,
    "type": "2x2CornerSlope",
    "usingNewColor": true,
    "user": "866f58c7e2dbe62c376ca77f2c0afd0c"
  },
  {
    "pos": {
      "x": -0.02452957,
      "y": 0.9586399,
      "z": -2.203526
    },
    "rot": {
      "w": 1.311342e-7,
      "x": 0,
      "y": -1,
      "z": 0
    },
    "color": -9535771,
    "materialId": 0,
    "type": "2x8",
    "usingNewColor": true,
    "user": "866f58c7e2dbe62c376ca77f2c0afd0c"
  },
  {
    "pos": {
      "x": -0.1923912,
      "y": 1.092912,
      "z": -1.642811
    },
    "rot": {
      "w": -0.7071067,
      "x": 0,
      "y": -0.7071069,
      "z": 0
    },
    "color": -9535771,
    "materialId": 0,
    "type": "2x2CornerSlope",
    "usingNewColor": true,
    "user": "866f58c7e2dbe62c376ca77f2c0afd0c"
  },
  {
    "pos": {
      "x": 0.03148612,
      "y": 1.092912,
      "z": -2.203587
    },
    "rot": {
      "w": 0.7071069,
      "x": 0,
      "y": -0.7071067,
      "z": 0
    },
    "color": -9535771,
    "materialId": 0,
    "type": "2x2Slope",
    "usingNewColor": true,
    "user": "866f58c7e2dbe62c376ca77f2c0afd0c"
  },
  {
    "pos": {
      "x": 0.2840564,
      "y": 0.802132,
      "z": -1.754739
    },
    "rot": {
      "w": -0.7071067,
      "x": 0,
      "y": -0.7071069,
      "z": 0
    },
    "color": -9535771,
    "materialId": 0,
    "type": "1x2Plate",
    "usingNewColor": true,
    "user": "866f58c7e2dbe62c376ca77f2c0afd0c"
  },
  {
    "pos": {
      "x": -0.3326446,
      "y": 0.802132,
      "z": -2.231503
    },
    "rot": {
      "w": -0.7071066,
      "x": 0,
      "y": -0.7071069,
      "z": 0
    },
    "color": -3855316,
    "materialId": 0,
    "type": "FlatPlant",
    "usingNewColor": true,
    "user": "866f58c7e2dbe62c376ca77f2c0afd0c"
  },
  {
    "pos": {
      "x": -0.08056385,
      "y": 1.092912,
      "z": -2.203587
    },
    "rot": {
      "w": 0.7071069,
      "x": 0,
      "y": -0.7071067,
      "z": 0
    },
    "color": -9535771,
    "materialId": 0,
    "type": "2x2Slope",
    "usingNewColor": true,
    "user": "866f58c7e2dbe62c376ca77f2c0afd0c"
  },
  {
    "pos": {
      "x": 0.3682308,
      "y": 1.025776,
      "z": -1.923187
    },
    "rot": {
      "w": -0.7071073,
      "x": 0,
      "y": 0.7071063,
      "z": 0
    },
    "color": -9535771,
    "materialId": 0,
    "type": "2x8",
    "usingNewColor": true,
    "user": "866f58c7e2dbe62c376ca77f2c0afd0c"
  },
  {
    "pos": {
      "x": 0.200044,
      "y": 0.757232,
      "z": -1.754802
    },
    "rot": {
      "w": -1,
      "x": 0,
      "y": -8.742278e-8,
      "z": 0
    },
    "color": -9535771,
    "materialId": 0,
    "type": "4x2",
    "usingNewColor": true,
    "user": "866f58c7e2dbe62c376ca77f2c0afd0c"
  },
  {
    "pos": {
      "x": -0.1925822,
      "y": 1.09294,
      "z": -1.979525
    },
    "rot": {
      "w": -1,
      "x": 0,
      "y": -1.03316e-7,
      "z": 0
    },
    "color": -9535771,
    "materialId": 0,
    "type": "2x2Slope",
    "usingNewColor": true,
    "user": "866f58c7e2dbe62c376ca77f2c0afd0c"
  },
  {
    "pos": {
      "x": 0.3682314,
      "y": 0.757232,
      "z": -1.923189
    },
    "rot": {
      "w": -0.7071068,
      "x": 0,
      "y": -0.7071069,
      "z": 0
    },
    "color": -9535771,
    "materialId": 0,
    "type": "2x8",
    "usingNewColor": true,
    "user": "866f58c7e2dbe62c376ca77f2c0afd0c"
  },
  {
    "pos": {
      "x": -0.1925821,
      "y": 1.09294,
      "z": -1.755526
    },
    "rot": {
      "w": -1,
      "x": 0,
      "y": -1.03316e-7,
      "z": 0
    },
    "color": -9535771,
    "materialId": 0,
    "type": "2x2Slope",
    "usingNewColor": true,
    "user": "866f58c7e2dbe62c376ca77f2c0afd0c"
  },
  {
    "pos": {
      "x": -0.1365762,
      "y": 1.160048,
      "z": -2.147575
    },
    "rot": {
      "w": 1,
      "x": 0,
      "y": 4.371139e-8,
      "z": 0
    },
    "color": -9667359,
    "materialId": 0,
    "type": "2x2CornerSlope",
    "usingNewColor": true,
    "user": "866f58c7e2dbe62c376ca77f2c0afd0c"
  },
  {
    "pos": {
      "x": 0.2559891,
      "y": 1.092912,
      "z": -1.642586
    },
    "rot": {
      "w": -0.7071067,
      "x": 0,
      "y": -0.7071069,
      "z": 0
    },
    "color": -9667359,
    "materialId": 0,
    "type": "2x2Slope",
    "usingNewColor": true,
    "user": "866f58c7e2dbe62c376ca77f2c0afd0c"
  },
  {
    "pos": {
      "x": 0.03127389,
      "y": 1.361456,
      "z": -1.979348
    },
    "rot": {
      "w": 1,
      "x": 0,
      "y": 4.371139e-8,
      "z": 0
    },
    "color": -9667359,
    "materialId": 0,
    "type": "2x2CornerSlope",
    "usingNewColor": true,
    "user": "866f58c7e2dbe62c376ca77f2c0afd0c"
  },
  {
    "pos": {
      "x": 0.2560524,
      "y": 1.227184,
      "z": -1.754674
    },
    "rot": {
      "w": 3.715369e-7,
      "x": 0,
      "y": -1,
      "z": 0
    },
    "color": -9667359,
    "materialId": 0,
    "type": "2x2CornerSlope",
    "usingNewColor": true,
    "user": "866f58c7e2dbe62c376ca77f2c0afd0c"
  },
  {
    "pos": {
      "x": -0.3326446,
      "y": 0.802132,
      "z": -1.782902
    },
    "rot": {
      "w": -0.7071066,
      "x": 0,
      "y": -0.7071069,
      "z": 0
    },
    "color": -65536,
    "materialId": 0,
    "type": "FlatPlant",
    "usingNewColor": true,
    "user": "866f58c7e2dbe62c376ca77f2c0afd0c"
  },
  {
    "pos": {
      "x": 0.3120017,
      "y": 1.160048,
      "z": -1.698598
    },
    "rot": {
      "w": 2.225253e-7,
      "x": 0,
      "y": -1,
      "z": 0
    },
    "color": -9667359,
    "materialId": 0,
    "type": "2x2CornerSlope",
    "usingNewColor": true,
    "user": "866f58c7e2dbe62c376ca77f2c0afd0c"
  },
  {
    "pos": {
      "x": -0.3326446,
      "y": 0.802132,
      "z": -1.726927
    },
    "rot": {
      "w": -0.7071066,
      "x": 0,
      "y": -0.7071069,
      "z": 0
    },
    "color": -65536,
    "materialId": 0,
    "type": "FlatPlant",
    "usingNewColor": true,
    "user": "866f58c7e2dbe62c376ca77f2c0afd0c"
  },
  {
    "pos": {
      "x": 0.03133645,
      "y": 1.227184,
      "z": -2.091436
    },
    "rot": {
      "w": 0.7071069,
      "x": 0,
      "y": -0.7071067,
      "z": 0
    },
    "color": -9667359,
    "materialId": 0,
    "type": "2x2Slope",
    "usingNewColor": true,
    "user": "866f58c7e2dbe62c376ca77f2c0afd0c"
  },
  {
    "pos": {
      "x": 0.3682302,
      "y": 0.9586399,
      "z": -1.923185
    },
    "rot": {
      "w": -0.7071064,
      "x": 0,
      "y": -0.7071072,
      "z": 0
    },
    "color": -9535771,
    "materialId": 0,
    "type": "2x8",
    "usingNewColor": true,
    "user": "866f58c7e2dbe62c376ca77f2c0afd0c"
  },
  {
    "pos": {
      "x": 0.3117011,
      "y": 1.025776,
      "z": -2.203527
    },
    "rot": {
      "w": 1.311342e-7,
      "x": 0,
      "y": -1,
      "z": 0
    },
    "color": -9535771,
    "materialId": 0,
    "type": "4x2",
    "usingNewColor": true,
    "user": "866f58c7e2dbe62c376ca77f2c0afd0c"
  },
  {
    "pos": {
      "x": 0.1721066,
      "y": 0.802132,
      "z": -1.754865
    },
    "rot": {
      "w": -1,
      "x": 0,
      "y": -1.748456e-7,
      "z": 0
    },
    "color": -9535771,
    "materialId": 0,
    "type": "2x3Tile",
    "usingNewColor": true,
    "user": "866f58c7e2dbe62c376ca77f2c0afd0c"
  },
  {
    "pos": {
      "x": -0.2766952,
      "y": 0.802132,
      "z": -2.063478
    },
    "rot": {
      "w": -0.7071066,
      "x": 0,
      "y": -0.7071069,
      "z": 0
    },
    "color": -3855316,
    "materialId": 0,
    "type": "ThreeLeafedPlant",
    "usingNewColor": true,
    "user": "866f58c7e2dbe62c376ca77f2c0afd0c"
  },
  {
    "pos": {
      "x": -0.3326446,
      "y": 0.802132,
      "z": -2.175528
    },
    "rot": {
      "w": -0.7071066,
      "x": 0,
      "y": -0.7071069,
      "z": 0
    },
    "color": -3855316,
    "materialId": 0,
    "type": "FlatPlant",
    "usingNewColor": true,
    "user": "866f58c7e2dbe62c376ca77f2c0afd0c"
  },
  {
    "pos": {
      "x": 0.3122185,
      "y": 1.160048,
      "z": -1.811225
    },
    "rot": {
      "w": 6.079713e-7,
      "x": 0,
      "y": -1,
      "z": 0
    },
    "color": -9667359,
    "materialId": 0,
    "type": "2x2Slope",
    "usingNewColor": true,
    "user": "866f58c7e2dbe62c376ca77f2c0afd0c"
  },
  {
    "pos": {
      "x": 0.255723,
      "y": 0.8915039,
      "z": -2.203527
    },
    "rot": {
      "w": 1.311342e-7,
      "x": 0,
      "y": -1,
      "z": 0
    },
    "color": -9535771,
    "materialId": 0,
    "type": "2x6",
    "usingNewColor": true,
    "user": "866f58c7e2dbe62c376ca77f2c0afd0c"
  },
  {
    "pos": {
      "x": -0.136507,
      "y": 1.160076,
      "z": -1.923425
    },
    "rot": {
      "w": -1,
      "x": 0,
      "y": -1.907388e-7,
      "z": 0
    },
    "color": -9667359,
    "materialId": 0,
    "type": "2x2Slope",
    "usingNewColor": true,
    "user": "866f58c7e2dbe62c376ca77f2c0afd0c"
  },
  {
    "pos": {
      "x": 0.3682937,
      "y": 0.8915039,
      "z": -2.091174
    },
    "rot": {
      "w": 3.119323e-7,
      "x": 0,
      "y": -1,
      "z": 0
    },
    "color": -9535771,
    "materialId": 0,
    "type": "2x2",
    "usingNewColor": true,
    "user": "866f58c7e2dbe62c376ca77f2c0afd0c"
  },
  {
    "pos": {
      "x": -0.2204947,
      "y": 0.925404,
      "z": -1.755561
    },
    "rot": {
      "w": -0.7071069,
      "x": 0,
      "y": 0.7071066,
      "z": 0
    },
    "color": -9535771,
    "materialId": 0,
    "type": "1x2Window",
    "usingNewColor": true,
    "user": "866f58c7e2dbe62c376ca77f2c0afd0c"
  },
  {
    "pos": {
      "x": 0.1435579,
      "y": 1.092912,
      "z": -1.642811
    },
    "rot": {
      "w": -0.7071067,
      "x": 0,
      "y": -0.7071069,
      "z": 0
    },
    "color": -9667359,
    "materialId": 0,
    "type": "2x2Slope",
    "usingNewColor": true,
    "user": "866f58c7e2dbe62c376ca77f2c0afd0c"
  },
  {
    "pos": {
      "x": -0.02461416,
      "y": 1.160048,
      "z": -2.147512
    },
    "rot": {
      "w": 0.7071069,
      "x": 0,
      "y": -0.7071067,
      "z": 0
    },
    "color": -9667359,
    "materialId": 0,
    "type": "2x2Slope",
    "usingNewColor": true,
    "user": "866f58c7e2dbe62c376ca77f2c0afd0c"
  },
  {
    "pos": {
      "x": -0.1924569,
      "y": 0.8243679,
      "z": -2.091476
    },
    "rot": {
      "w": 1.03316e-7,
      "x": 0,
      "y": -1,
      "z": 0
    },
    "color": -9535771,
    "materialId": 0,
    "type": "2x2",
    "usingNewColor": true,
    "user": "866f58c7e2dbe62c376ca77f2c0afd0c"
  },
  {
    "pos": {
      "x": 0.2561431,
      "y": 1.227184,
      "z": -1.867325
    },
    "rot": {
      "w": 6.079713e-7,
      "x": 0,
      "y": -1,
      "z": 0
    },
    "color": -9667359,
    "materialId": 0,
    "type": "2x2Slope",
    "usingNewColor": true,
    "user": "866f58c7e2dbe62c376ca77f2c0afd0c"
  },
  {
    "pos": {
      "x": 0.1999511,
      "y": 0.9586399,
      "z": -1.642649
    },
    "rot": {
      "w": 1.311342e-7,
      "x": 0,
      "y": -1,
      "z": 0
    },
    "color": -9535771,
    "materialId": 0,
    "type": "2x8",
    "usingNewColor": true,
    "user": "866f58c7e2dbe62c376ca77f2c0afd0c"
  },
  {
    "pos": {
      "x": -0.2766952,
      "y": 0.802132,
      "z": -2.175528
    },
    "rot": {
      "w": -0.7071066,
      "x": 0,
      "y": -0.7071069,
      "z": 0
    },
    "color": -65536,
    "materialId": 0,
    "type": "ThreeLeafedPlant",
    "usingNewColor": true,
    "user": "866f58c7e2dbe62c376ca77f2c0afd0c"
  }
]