[
  {
    "pos": {
      "x": 0.1438067,
      "y": 0.8243679,
      "z": 3.512099
    },
    "rot": {
      "w": 0.7071069,
      "x": 0,
      "y": -0.7071067,
      "z": 0
    },
    "color": -9535771,
    "materialId": 0,
    "type": "2x2",
    "usingNewColor": true,
    "user": "a353b2a976b01e8433a9aaeb8dee760b"
  },
  {
    "pos": {
      "x": 0.1438127,
      "y": 1.495728,
      "z": 3.399855
    },
    "rot": {
      "w": -0.707106,
      "x": 0,
      "y": -0.7071076,
      "z": 0
    },
    "color": -9535771,
    "materialId": 0,
    "type": "2x6",
    "usingNewColor": true,
    "user": "a353b2a976b01e8433a9aaeb8dee760b"
  },
  {
    "pos": {
      "x": 0.7326575,
      "y": 0.757232,
      "z": 3.091662
    },
    "rot": {
      "w": -4.371139e-8,
      "x": 0,
      "y": 1,
      "z": 0
    },
    "color": -9535771,
    "materialId": 0,
    "type": "1x1_1FaceSideStud",
    "usingNewColor": true,
    "user": "a353b2a976b01e8433a9aaeb8dee760b"
  },
  {
    "pos": {
      "x": 0.143813,
      "y": 0.8915039,
      "z": 3.287803
    },
    "rot": {
      "w": 0.7071069,
      "x": 0,
      "y": -0.7071067,
      "z": 0
    },
    "color": -9535771,
    "materialId": 0,
    "type": "2x2",
    "usingNewColor": true,
    "user": "a353b2a976b01e8433a9aaeb8dee760b"
  },
  {
    "pos": {
      "x": 0.143813,
      "y": 1.29432,
      "z": 3.399854
    },
    "rot": {
      "w": -0.7071064,
      "x": 0,
      "y": -0.7071072,
      "z": 0
    },
    "color": -9535771,
    "materialId": 0,
    "type": "2x6",
    "usingNewColor": true,
    "user": "a353b2a976b01e8433a9aaeb8dee760b"
  },
  {
    "pos": {
      "x": 0.1438128,
      "y": 0.8243679,
      "z": 3.287803
    },
    "rot": {
      "w": 0.7071069,
      "x": 0,
      "y": -0.7071067,
      "z": 0
    },
    "color": -9535771,
    "materialId": 0,
    "type": "2x2",
    "usingNewColor": true,
    "user": "a353b2a976b01e8433a9aaeb8dee760b"
  },
  {
    "pos": {
      "x": -0.1645448,
      "y": 0.7914959,
      "z": 2.895399
    },
    "rot": {
      "w": -0.7071069,
      "x": 0,
      "y": 0.7071068,
      "z": 0
    },
    "color": -9535771,
    "materialId": 0,
    "type": "1x2Window",
    "usingNewColor": true,
    "user": "a353b2a976b01e8433a9aaeb8dee760b"
  },
  {
    "pos": {
      "x": 0.1438122,
      "y": 1.63,
      "z": 3.287906
    },
    "rot": {
      "w": -0.7071059,
      "x": 0,
      "y": -0.7071077,
      "z": 0
    },
    "color": -9535771,
    "materialId": 0,
    "type": "2x2",
    "usingNewColor": true,
    "user": "a353b2a976b01e8433a9aaeb8dee760b"
  },
  {
    "pos": {
      "x": 0.1438129,
      "y": 1.361456,
      "z": 3.399855
    },
    "rot": {
      "w": -0.7071062,
      "x": 0,
      "y": -0.7071074,
      "z": 0
    },
    "color": -9535771,
    "materialId": 0,
    "type": "2x6",
    "usingNewColor": true,
    "user": "a353b2a976b01e8433a9aaeb8dee760b"
  },
  {
    "pos": {
      "x": 0.1438129,
      "y": 1.227184,
      "z": 3.399854
    },
    "rot": {
      "w": -0.7071065,
      "x": 0,
      "y": -0.7071071,
      "z": 0
    },
    "color": -9535771,
    "materialId": 0,
    "type": "2x6",
    "usingNewColor": true,
    "user": "a353b2a976b01e8433a9aaeb8dee760b"
  },
  {
    "pos": {
      "x": 0.1158313,
      "y": 0.757232,
      "z": 3.512163
    },
    "rot": {
      "w": -4.371139e-8,
      "x": 0,
      "y": 1,
      "z": 0
    },
    "color": -9535771,
    "materialId": 0,
    "type": "2x3",
    "usingNewColor": true,
    "user": "a353b2a976b01e8433a9aaeb8dee760b"
  },
  {
    "pos": {
      "x": 0.1438069,
      "y": 0.8915039,
      "z": 3.512099
    },
    "rot": {
      "w": 0.7071069,
      "x": 0,
      "y": -0.7071067,
      "z": 0
    },
    "color": -9535771,
    "materialId": 0,
    "type": "2x2",
    "usingNewColor": true,
    "user": "a353b2a976b01e8433a9aaeb8dee760b"
  },
  {
    "pos": {
      "x": 0.1438133,
      "y": 0.9586399,
      "z": 3.287802
    },
    "rot": {
      "w": 0.7071069,
      "x": 0,
      "y": -0.7071067,
      "z": 0
    },
    "color": -9535771,
    "materialId": 0,
    "type": "2x2",
    "usingNewColor": true,
    "user": "a353b2a976b01e8433a9aaeb8dee760b"
  },
  {
    "pos": {
      "x": 0.1438135,
      "y": 1.025776,
      "z": 3.287802
    },
    "rot": {
      "w": 0.7071069,
      "x": 0,
      "y": -0.7071067,
      "z": 0
    },
    "color": -9535771,
    "materialId": 0,
    "type": "2x2",
    "usingNewColor": true,
    "user": "a353b2a976b01e8433a9aaeb8dee760b"
  },
  {
    "pos": {
      "x": 0.1438129,
      "y": 1.160048,
      "z": 3.399854
    },
    "rot": {
      "w": -0.7071066,
      "x": 0,
      "y": -0.7071069,
      "z": 0
    },
    "color": -9535771,
    "materialId": 0,
    "type": "2x6",
    "usingNewColor": true,
    "user": "a353b2a976b01e8433a9aaeb8dee760b"
  },
  {
    "pos": {
      "x": 0.1438127,
      "y": 1.428592,
      "z": 3.399855
    },
    "rot": {
      "w": -0.7071061,
      "x": 0,
      "y": -0.7071075,
      "z": 0
    },
    "color": -9535771,
    "materialId": 0,
    "type": "2x6",
    "usingNewColor": true,
    "user": "a353b2a976b01e8433a9aaeb8dee760b"
  },
  {
    "pos": {
      "x": 0.1438071,
      "y": 0.9586399,
      "z": 3.512099
    },
    "rot": {
      "w": 0.7071069,
      "x": 0,
      "y": -0.7071067,
      "z": 0
    },
    "color": -9535771,
    "materialId": 0,
    "type": "2x2",
    "usingNewColor": true,
    "user": "a353b2a976b01e8433a9aaeb8dee760b"
  },
  {
    "pos": {
      "x": 0.1437494,
      "y": 1.562864,
      "z": 3.231893
    },
    "rot": {
      "w": -1,
      "x": 0,
      "y": -0.000001206002,
      "z": 0
    },
    "color": -9535771,
    "materialId": 0,
    "type": "2x2",
    "usingNewColor": true,
    "user": "a353b2a976b01e8433a9aaeb8dee760b"
  },
  {
    "pos": {
      "x": 0.1438073,
      "y": 1.025776,
      "z": 3.512099
    },
    "rot": {
      "w": 0.7071069,
      "x": 0,
      "y": -0.7071067,
      "z": 0
    },
    "color": -9535771,
    "materialId": 0,
    "type": "2x2",
    "usingNewColor": true,
    "user": "a353b2a976b01e8433a9aaeb8dee760b"
  },
  {
    "pos": {
      "x": 0.1158379,
      "y": 0.757232,
      "z": 3.287866
    },
    "rot": {
      "w": -4.371139e-8,
      "x": 0,
      "y": 1,
      "z": 0
    },
    "color": -9535771,
    "materialId": 0,
    "type": "2x3",
    "usingNewColor": true,
    "user": "a353b2a976b01e8433a9aaeb8dee760b"
  },
  {
    "pos": {
      "x": 0.143813,
      "y": 1.092912,
      "z": 3.399853
    },
    "rot": {
      "w": -0.7071068,
      "x": 0,
      "y": -0.7071069,
      "z": 0
    },
    "color": -9535771,
    "materialId": 0,
    "type": "2x6",
    "usingNewColor": true,
    "user": "a353b2a976b01e8433a9aaeb8dee760b"
  },
  {
    "pos": {
      "x": -0.1645448,
      "y": 0.7914959,
      "z": 3.007549
    },
    "rot": {
      "w": -0.7071069,
      "x": 0,
      "y": 0.7071068,
      "z": 0
    },
    "color": -9535771,
    "materialId": 0,
    "type": "1x2Window",
    "usingNewColor": true,
    "user": "a353b2a976b01e8433a9aaeb8dee760b"
  }
]