[
  {
    "pos": {
      "x": 0.08440118,
      "y": 0.8323075,
      "z": -1.302682
    },
    "rot": {
      "w": 0.5623391,
      "x": 0.008840892,
      "y": -0.8267965,
      "z": 0.01020491
    },
    "color": -5820200,
    "materialId": 0,
    "type": "2x6",
    "usingNewColor": true,
    "user": "376a0cddd70386103ba0e351a083eda4"
  },
  {
    "pos": {
      "x": 0.1032141,
      "y": 0.8995949,
      "z": -1.355207
    },
    "rot": {
      "w": -0.5623392,
      "x": -0.008840892,
      "y": 0.8267965,
      "z": -0.01020491
    },
    "color": -5820200,
    "materialId": 0,
    "type": "2x6",
    "usingNewColor": true,
    "user": "376a0cddd70386103ba0e351a083eda4"
  }
]